[
    {
        "%vlocity_namespace%__DomainObjectAPIName__c": "Formula",
        "%vlocity_namespace%__DomainObjectCreationOrder__c": 0,
        "%vlocity_namespace%__DomainObjectFieldAPIName__c": "Formula",
        "%vlocity_namespace%__FormulaOrder__c": 1,
        "%vlocity_namespace%__FormulaResultPath__c": "PublishedData:SuccessFields",
        "%vlocity_namespace%__Formula__c": "APIResponse:syncSuccessFields",
        "%vlocity_namespace%__GlobalKey__c": "4fb6f0de-07c2-8d50-fb34-f896504a4c24",
        "%vlocity_namespace%__IsDisabled__c": false,
        "%vlocity_namespace%__IsRequiredForUpsert__c": false,
        "%vlocity_namespace%__MapId__c": "VPL-UpdateMetaPublishStatus31439233203995487",
        "%vlocity_namespace%__OMplusSyncEnabled__c": false,
        "%vlocity_namespace%__UpsertKey__c": false,
        "Name": "VPL-UpdateMetaPublishStatus",
        "VlocityDataPackType": "SObject",
        "VlocityRecordSObjectType": "%vlocity_namespace%__DRMapItem__c"
    },
    {
        "%vlocity_namespace%__DomainObjectAPIName__c": "Formula",
        "%vlocity_namespace%__DomainObjectCreationOrder__c": 0,
        "%vlocity_namespace%__DomainObjectFieldAPIName__c": "Formula",
        "%vlocity_namespace%__FormulaOrder__c": 2,
        "%vlocity_namespace%__FormulaResultPath__c": "PublishedData:SuccessAttributes",
        "%vlocity_namespace%__Formula__c": "APIResponse:successAttributes",
        "%vlocity_namespace%__GlobalKey__c": "39566747-b941-293b-351b-bd1ded299ea3",
        "%vlocity_namespace%__IsDisabled__c": false,
        "%vlocity_namespace%__IsRequiredForUpsert__c": false,
        "%vlocity_namespace%__MapId__c": "VPL-UpdateMetaPublishStatus7124148857261654",
        "%vlocity_namespace%__OMplusSyncEnabled__c": false,
        "%vlocity_namespace%__UpsertKey__c": false,
        "Name": "VPL-UpdateMetaPublishStatus",
        "VlocityDataPackType": "SObject",
        "VlocityRecordSObjectType": "%vlocity_namespace%__DRMapItem__c"
    },
    {
        "%vlocity_namespace%__DomainObjectAPIName__c": "Formula",
        "%vlocity_namespace%__DomainObjectCreationOrder__c": 0,
        "%vlocity_namespace%__DomainObjectFieldAPIName__c": "Formula",
        "%vlocity_namespace%__FormulaOrder__c": 3,
        "%vlocity_namespace%__FormulaResultPath__c": "PublishedData:notFoundObjects",
        "%vlocity_namespace%__Formula__c": "notFoundObjects",
        "%vlocity_namespace%__GlobalKey__c": "fd830248-39c1-6512-a186-8286c4f0b666",
        "%vlocity_namespace%__IsDisabled__c": false,
        "%vlocity_namespace%__IsRequiredForUpsert__c": false,
        "%vlocity_namespace%__MapId__c": "VPL-UpdateMetaPublishStatus42897014424170554",
        "%vlocity_namespace%__OMplusSyncEnabled__c": false,
        "%vlocity_namespace%__UpsertKey__c": false,
        "Name": "VPL-UpdateMetaPublishStatus",
        "VlocityDataPackType": "SObject",
        "VlocityRecordSObjectType": "%vlocity_namespace%__DRMapItem__c"
    },
    {
        "%vlocity_namespace%__DomainObjectAPIName__c": "Formula",
        "%vlocity_namespace%__DomainObjectCreationOrder__c": 0,
        "%vlocity_namespace%__DomainObjectFieldAPIName__c": "Formula",
        "%vlocity_namespace%__FormulaOrder__c": 4,
        "%vlocity_namespace%__FormulaResultPath__c": "PublishedData:notFoundFields",
        "%vlocity_namespace%__Formula__c": "notFoundFields",
        "%vlocity_namespace%__GlobalKey__c": "73d28479-c4d3-af25-0ac0-925f3c6b87b0",
        "%vlocity_namespace%__IsDisabled__c": false,
        "%vlocity_namespace%__IsRequiredForUpsert__c": false,
        "%vlocity_namespace%__MapId__c": "VPL-UpdateMetaPublishStatus48044817808719054",
        "%vlocity_namespace%__OMplusSyncEnabled__c": false,
        "%vlocity_namespace%__UpsertKey__c": false,
        "Name": "VPL-UpdateMetaPublishStatus",
        "VlocityDataPackType": "SObject",
        "VlocityRecordSObjectType": "%vlocity_namespace%__DRMapItem__c"
    },
    {
        "%vlocity_namespace%__DomainObjectAPIName__c": "Formula",
        "%vlocity_namespace%__DomainObjectCreationOrder__c": 0,
        "%vlocity_namespace%__DomainObjectFieldAPIName__c": "Formula",
        "%vlocity_namespace%__FormulaOrder__c": 5,
        "%vlocity_namespace%__FormulaResultPath__c": "PublishedData:syncFailureFields",
        "%vlocity_namespace%__Formula__c": "syncFailureFields",
        "%vlocity_namespace%__GlobalKey__c": "45ecc08d-c462-694b-f16a-0f88c4d5ea29",
        "%vlocity_namespace%__IsDisabled__c": false,
        "%vlocity_namespace%__IsRequiredForUpsert__c": false,
        "%vlocity_namespace%__MapId__c": "VPL-UpdateMetaPublishStatus4573229326395769",
        "%vlocity_namespace%__OMplusSyncEnabled__c": false,
        "%vlocity_namespace%__UpsertKey__c": false,
        "Name": "VPL-UpdateMetaPublishStatus",
        "VlocityDataPackType": "SObject",
        "VlocityRecordSObjectType": "%vlocity_namespace%__DRMapItem__c"
    },
    {
        "%vlocity_namespace%__DomainObjectAPIName__c": "%vlocity_namespace%__VlocityTrackingEntry__c",
        "%vlocity_namespace%__DomainObjectCreationOrder__c": 1,
        "%vlocity_namespace%__DomainObjectFieldAPIName__c": "%vlocity_namespace%__ContextId__c",
        "%vlocity_namespace%__GlobalKey__c": "81eceb9f-62eb-cfc2-53dd-f9cf302fe3ce",
        "%vlocity_namespace%__InterfaceFieldAPIName__c": "CCLogKey",
        "%vlocity_namespace%__IsDisabled__c": false,
        "%vlocity_namespace%__IsRequiredForUpsert__c": false,
        "%vlocity_namespace%__MapId__c": "VPL-UpdateMetaPublishStatusCustom85",
        "%vlocity_namespace%__OMplusSyncEnabled__c": false,
        "%vlocity_namespace%__UpsertKey__c": false,
        "Name": "VPL-UpdateMetaPublishStatus",
        "VlocityDataPackType": "SObject",
        "VlocityRecordSObjectType": "%vlocity_namespace%__DRMapItem__c"
    },
    {
        "%vlocity_namespace%__DomainObjectAPIName__c": "%vlocity_namespace%__VlocityTrackingEntry__c",
        "%vlocity_namespace%__DomainObjectCreationOrder__c": 1,
        "%vlocity_namespace%__DomainObjectFieldAPIName__c": "%vlocity_namespace%__Data__c",
        "%vlocity_namespace%__GlobalKey__c": "0138638a-2ffc-b4ca-58ed-cb2343f566f9",
        "%vlocity_namespace%__InterfaceFieldAPIName__c": "PublishedData",
        "%vlocity_namespace%__IsDisabled__c": false,
        "%vlocity_namespace%__IsRequiredForUpsert__c": false,
        "%vlocity_namespace%__MapId__c": "VPL-UpdateMetaPublishStatus6234270406770142",
        "%vlocity_namespace%__OMplusSyncEnabled__c": false,
        "%vlocity_namespace%__UpsertKey__c": false,
        "Name": "VPL-UpdateMetaPublishStatus",
        "VlocityDataPackType": "SObject",
        "VlocityRecordSObjectType": "%vlocity_namespace%__DRMapItem__c"
    },
    {
        "%vlocity_namespace%__DomainObjectAPIName__c": "%vlocity_namespace%__VlocityTrackingEntry__c",
        "%vlocity_namespace%__DomainObjectCreationOrder__c": 1,
        "%vlocity_namespace%__DomainObjectFieldAPIName__c": "%vlocity_namespace%__Timestamp__c",
        "%vlocity_namespace%__GlobalKey__c": "8ca0466c-3bbf-3bad-06cc-c30c68235e5e",
        "%vlocity_namespace%__InterfaceFieldAPIName__c": "publishTimestamp",
        "%vlocity_namespace%__IsDisabled__c": false,
        "%vlocity_namespace%__IsRequiredForUpsert__c": false,
        "%vlocity_namespace%__MapId__c": "VPL-UpdateMetaPublishStatus6244708214605814",
        "%vlocity_namespace%__OMplusSyncEnabled__c": false,
        "%vlocity_namespace%__UpsertKey__c": false,
        "Name": "VPL-UpdateMetaPublishStatus",
        "VlocityDataPackType": "SObject",
        "VlocityRecordSObjectType": "%vlocity_namespace%__DRMapItem__c"
    },
    {
        "%vlocity_namespace%__DomainObjectAPIName__c": "%vlocity_namespace%__VlocityTrackingEntry__c",
        "%vlocity_namespace%__DomainObjectCreationOrder__c": 1,
        "%vlocity_namespace%__DomainObjectFieldAPIName__c": "%vlocity_namespace%__TrackingService__c",
        "%vlocity_namespace%__GlobalKey__c": "d8786668-beae-d98a-45d7-ba9328cf8b4b",
        "%vlocity_namespace%__InterfaceFieldAPIName__c": "publishStatus",
        "%vlocity_namespace%__IsDisabled__c": false,
        "%vlocity_namespace%__IsRequiredForUpsert__c": false,
        "%vlocity_namespace%__MapId__c": "VPL-UpdateMetaPublishStatus9295785718012648",
        "%vlocity_namespace%__OMplusSyncEnabled__c": false,
        "%vlocity_namespace%__UpsertKey__c": false,
        "Name": "VPL-UpdateMetaPublishStatus",
        "VlocityDataPackType": "SObject",
        "VlocityRecordSObjectType": "%vlocity_namespace%__DRMapItem__c"
    },
    {
        "%vlocity_namespace%__ConfigurationValue__c": "FAKEMAPPING",
        "%vlocity_namespace%__DomainObjectAPIName__c": "%vlocity_namespace%__VlocityTrackingEntry__c",
        "%vlocity_namespace%__DomainObjectCreationOrder__c": 1,
        "%vlocity_namespace%__DomainObjectFieldAPIName__c": "Id",
        "%vlocity_namespace%__FilterOperator__c": "=",
        "%vlocity_namespace%__GlobalKey__c": "34076432-bb6c-da24-e74e-b066f7902ad6",
        "%vlocity_namespace%__IsDisabled__c": true,
        "%vlocity_namespace%__IsRequiredForUpsert__c": false,
        "%vlocity_namespace%__MapId__c": "VPL-UpdateMetaPublishStatus8596593500412208",
        "%vlocity_namespace%__OMplusSyncEnabled__c": false,
        "%vlocity_namespace%__UpsertKey__c": false,
        "Name": "VPL-UpdateMetaPublishStatus",
        "VlocityDataPackType": "SObject",
        "VlocityRecordSObjectType": "%vlocity_namespace%__DRMapItem__c"
    },
    {
        "%vlocity_namespace%__DefaultValue__c": "CommerceCloud-MetadataPublish",
        "%vlocity_namespace%__DomainObjectAPIName__c": "%vlocity_namespace%__VlocityTrackingEntry__c",
        "%vlocity_namespace%__DomainObjectCreationOrder__c": 1,
        "%vlocity_namespace%__DomainObjectFieldAPIName__c": "Name",
        "%vlocity_namespace%__GlobalKey__c": "4f2225c5-9e7e-b3be-1b11-843c29cecf4b",
        "%vlocity_namespace%__IsDisabled__c": false,
        "%vlocity_namespace%__IsRequiredForUpsert__c": false,
        "%vlocity_namespace%__MapId__c": "VPL-UpdateMetaPublishStatus29725917856945316",
        "%vlocity_namespace%__OMplusSyncEnabled__c": false,
        "%vlocity_namespace%__UpsertKey__c": false,
        "Name": "VPL-UpdateMetaPublishStatus",
        "VlocityDataPackType": "SObject",
        "VlocityRecordSObjectType": "%vlocity_namespace%__DRMapItem__c"
    }
]