[
    {
        "%vlocity_namespace%__DomainObjectAPIName__c": "json",
        "%vlocity_namespace%__DomainObjectCreationOrder__c": 0,
        "%vlocity_namespace%__DomainObjectFieldAPIName__c": "Policy",
        "%vlocity_namespace%__FilterOperator__c": "=",
        "%vlocity_namespace%__FilterValue__c": "Id",
        "%vlocity_namespace%__FormulaOrder__c": 0,
        "%vlocity_namespace%__GlobalKey__c": "60423192-d419-ef42-cc4a-4e4358b835d2",
        "%vlocity_namespace%__InterfaceFieldAPIName__c": "Id",
        "%vlocity_namespace%__InterfaceObjectLookupOrder__c": 1,
        "%vlocity_namespace%__InterfaceObjectName__c": "Asset",
        "%vlocity_namespace%__IsDisabled__c": false,
        "%vlocity_namespace%__IsRequiredForUpsert__c": false,
        "%vlocity_namespace%__LinkCreatedIndex__c": 0,
        "%vlocity_namespace%__MapId__c": "VPL-np-ReadPolicyDetail-100-1Customa19f4000000chtuAAAItem0",
        "%vlocity_namespace%__OMplusSyncEnabled__c": false,
        "%vlocity_namespace%__UpsertKey__c": false,
        "Name": "port_ReadPolicyDetail_Card",
        "VlocityDataPackType": "SObject",
        "VlocityRecordSObjectType": "%vlocity_namespace%__DRMapItem__c"
    },
    {
        "%vlocity_namespace%__DomainObjectAPIName__c": "json",
        "%vlocity_namespace%__DomainObjectCreationOrder__c": 0,
        "%vlocity_namespace%__DomainObjectFieldAPIName__c": "Policy:Policyholder",
        "%vlocity_namespace%__FilterOperator__c": "=",
        "%vlocity_namespace%__FilterValue__c": "Policy:AccountId",
        "%vlocity_namespace%__FormulaOrder__c": 0,
        "%vlocity_namespace%__GlobalKey__c": "000c1f56-51b6-0d1f-6645-14e920e01381",
        "%vlocity_namespace%__InterfaceFieldAPIName__c": "Id",
        "%vlocity_namespace%__InterfaceObjectLookupOrder__c": 2,
        "%vlocity_namespace%__InterfaceObjectName__c": "Account",
        "%vlocity_namespace%__IsDisabled__c": false,
        "%vlocity_namespace%__IsRequiredForUpsert__c": false,
        "%vlocity_namespace%__LinkCreatedIndex__c": 0,
        "%vlocity_namespace%__MapId__c": "VPL-np-ReadPolicyDetail-100-1Customa19f4000000chtuAAAItem3",
        "%vlocity_namespace%__OMplusSyncEnabled__c": false,
        "%vlocity_namespace%__UpsertKey__c": false,
        "Name": "port_ReadPolicyDetail_Card",
        "VlocityDataPackType": "SObject",
        "VlocityRecordSObjectType": "%vlocity_namespace%__DRMapItem__c"
    },
    {
        "%vlocity_namespace%__DomainObjectAPIName__c": "json",
        "%vlocity_namespace%__DomainObjectCreationOrder__c": 0,
        "%vlocity_namespace%__DomainObjectFieldAPIName__c": "Policy:PrimaryProducerId",
        "%vlocity_namespace%__FilterOperator__c": "=",
        "%vlocity_namespace%__FilterValue__c": "Policy:%vlocity_namespace%__PrimaryProducerId__c",
        "%vlocity_namespace%__FormulaOrder__c": 0,
        "%vlocity_namespace%__GlobalKey__c": "fac4613d-c1ce-c7b3-f782-43485e1ce381",
        "%vlocity_namespace%__InterfaceFieldAPIName__c": "Id",
        "%vlocity_namespace%__InterfaceObjectLookupOrder__c": 3,
        "%vlocity_namespace%__InterfaceObjectName__c": "Contact",
        "%vlocity_namespace%__IsDisabled__c": false,
        "%vlocity_namespace%__IsRequiredForUpsert__c": false,
        "%vlocity_namespace%__LinkCreatedIndex__c": 0,
        "%vlocity_namespace%__MapId__c": "VPL-np-ReadPolicyDetail-100-1Customa19f4000000chtuAAAItem2",
        "%vlocity_namespace%__OMplusSyncEnabled__c": false,
        "%vlocity_namespace%__UpsertKey__c": false,
        "Name": "port_ReadPolicyDetail_Card",
        "VlocityDataPackType": "SObject",
        "VlocityRecordSObjectType": "%vlocity_namespace%__DRMapItem__c"
    },
    {
        "%vlocity_namespace%__DomainObjectAPIName__c": "json",
        "%vlocity_namespace%__DomainObjectCreationOrder__c": 0,
        "%vlocity_namespace%__DomainObjectFieldAPIName__c": "Policy:Carrier",
        "%vlocity_namespace%__FilterOperator__c": "=",
        "%vlocity_namespace%__FilterValue__c": "Policy:%vlocity_namespace%__CarrierId__c",
        "%vlocity_namespace%__FormulaOrder__c": 0,
        "%vlocity_namespace%__GlobalKey__c": "f1ccf83e-8e29-daf5-da4d-21cc42b32ccc",
        "%vlocity_namespace%__InterfaceFieldAPIName__c": "Id",
        "%vlocity_namespace%__InterfaceObjectLookupOrder__c": 4,
        "%vlocity_namespace%__InterfaceObjectName__c": "Account",
        "%vlocity_namespace%__IsDisabled__c": false,
        "%vlocity_namespace%__IsRequiredForUpsert__c": false,
        "%vlocity_namespace%__LinkCreatedIndex__c": 0,
        "%vlocity_namespace%__MapId__c": "VPL-np-ReadPolicyDetail-100-1Customa19f4000000chtuAAAItem1",
        "%vlocity_namespace%__OMplusSyncEnabled__c": false,
        "%vlocity_namespace%__UpsertKey__c": false,
        "Name": "port_ReadPolicyDetail_Card",
        "VlocityDataPackType": "SObject",
        "VlocityRecordSObjectType": "%vlocity_namespace%__DRMapItem__c"
    },
    {
        "%vlocity_namespace%__DomainObjectAPIName__c": "Formula",
        "%vlocity_namespace%__DomainObjectCreationOrder__c": 0,
        "%vlocity_namespace%__DomainObjectFieldAPIName__c": "Formula",
        "%vlocity_namespace%__FormulaOrder__c": 0,
        "%vlocity_namespace%__FormulaResultPath__c": "LoanAvailable",
        "%vlocity_namespace%__GlobalKey__c": "960258e4-cae6-db78-e2f1-97f50ece1e2f",
        "%vlocity_namespace%__IsDisabled__c": false,
        "%vlocity_namespace%__IsRequiredForUpsert__c": false,
        "%vlocity_namespace%__LinkCreatedIndex__c": 0,
        "%vlocity_namespace%__MapId__c": "VPL-np-ReadPolicyDetail-100-1Custom2059",
        "%vlocity_namespace%__OMplusSyncEnabled__c": false,
        "%vlocity_namespace%__UpsertKey__c": false,
        "Name": "port_ReadPolicyDetail_Card",
        "VlocityDataPackType": "SObject",
        "VlocityRecordSObjectType": "%vlocity_namespace%__DRMapItem__c"
    },
    {
        "%vlocity_namespace%__DomainObjectAPIName__c": "Formula",
        "%vlocity_namespace%__DomainObjectCreationOrder__c": 0,
        "%vlocity_namespace%__DomainObjectFieldAPIName__c": "Formula",
        "%vlocity_namespace%__FormulaOrder__c": 0,
        "%vlocity_namespace%__FormulaResultPath__c": "LoanBalance",
        "%vlocity_namespace%__GlobalKey__c": "38c82883-bae3-a274-0d87-4048efe954d3",
        "%vlocity_namespace%__IsDisabled__c": false,
        "%vlocity_namespace%__IsRequiredForUpsert__c": false,
        "%vlocity_namespace%__LinkCreatedIndex__c": 0,
        "%vlocity_namespace%__MapId__c": "VPL-np-ReadPolicyDetail-100-1Custom6498",
        "%vlocity_namespace%__OMplusSyncEnabled__c": false,
        "%vlocity_namespace%__UpsertKey__c": false,
        "Name": "port_ReadPolicyDetail_Card",
        "VlocityDataPackType": "SObject",
        "VlocityRecordSObjectType": "%vlocity_namespace%__DRMapItem__c"
    },
    {
        "%vlocity_namespace%__DomainObjectAPIName__c": "Formula",
        "%vlocity_namespace%__DomainObjectCreationOrder__c": 0,
        "%vlocity_namespace%__DomainObjectFieldAPIName__c": "Formula",
        "%vlocity_namespace%__FormulaOrder__c": 0,
        "%vlocity_namespace%__FormulaResultPath__c": "LoanInterestDue",
        "%vlocity_namespace%__GlobalKey__c": "41ef9ded-9bd3-4ae0-b014-fb646c55e486",
        "%vlocity_namespace%__IsDisabled__c": false,
        "%vlocity_namespace%__IsRequiredForUpsert__c": false,
        "%vlocity_namespace%__LinkCreatedIndex__c": 0,
        "%vlocity_namespace%__MapId__c": "VPL-np-ReadPolicyDetail-100-1Custom6101",
        "%vlocity_namespace%__OMplusSyncEnabled__c": false,
        "%vlocity_namespace%__UpsertKey__c": false,
        "Name": "port_ReadPolicyDetail_Card",
        "VlocityDataPackType": "SObject",
        "VlocityRecordSObjectType": "%vlocity_namespace%__DRMapItem__c"
    },
    {
        "%vlocity_namespace%__DomainObjectAPIName__c": "json",
        "%vlocity_namespace%__DomainObjectCreationOrder__c": 1,
        "%vlocity_namespace%__DomainObjectFieldAPIName__c": "Account:AccountId",
        "%vlocity_namespace%__FormulaOrder__c": 0,
        "%vlocity_namespace%__GlobalKey__c": "cc260bd5-6974-b240-163f-263ab968e2ed",
        "%vlocity_namespace%__InterfaceFieldAPIName__c": "Policy:AccountId",
        "%vlocity_namespace%__IsDisabled__c": false,
        "%vlocity_namespace%__IsRequiredForUpsert__c": false,
        "%vlocity_namespace%__LinkCreatedIndex__c": 0,
        "%vlocity_namespace%__MapId__c": "VPL-np-ReadPolicyDetail-100-1Customa19f4000000chtuAAAItem4",
        "%vlocity_namespace%__OMplusSyncEnabled__c": false,
        "%vlocity_namespace%__UpsertKey__c": false,
        "Name": "port_ReadPolicyDetail_Card",
        "VlocityDataPackType": "SObject",
        "VlocityRecordSObjectType": "%vlocity_namespace%__DRMapItem__c"
    },
    {
        "%vlocity_namespace%__DomainObjectAPIName__c": "json",
        "%vlocity_namespace%__DomainObjectCreationOrder__c": 1,
        "%vlocity_namespace%__DomainObjectFieldAPIName__c": "Account:AccountNumber",
        "%vlocity_namespace%__FormulaOrder__c": 0,
        "%vlocity_namespace%__GlobalKey__c": "49a442b7-d56f-56da-e68a-d65801df6380",
        "%vlocity_namespace%__InterfaceFieldAPIName__c": "Policy:Policyholder:AccountNumber",
        "%vlocity_namespace%__IsDisabled__c": false,
        "%vlocity_namespace%__IsRequiredForUpsert__c": false,
        "%vlocity_namespace%__LinkCreatedIndex__c": 0,
        "%vlocity_namespace%__MapId__c": "VPL-np-ReadPolicyDetail-100-1Customa19f4000000chtuAAAItem12",
        "%vlocity_namespace%__OMplusSyncEnabled__c": false,
        "%vlocity_namespace%__UpsertKey__c": false,
        "Name": "port_ReadPolicyDetail_Card",
        "VlocityDataPackType": "SObject",
        "VlocityRecordSObjectType": "%vlocity_namespace%__DRMapItem__c"
    },
    {
        "%vlocity_namespace%__DomainObjectAPIName__c": "json",
        "%vlocity_namespace%__DomainObjectCreationOrder__c": 1,
        "%vlocity_namespace%__DomainObjectFieldAPIName__c": "Account:Id",
        "%vlocity_namespace%__FormulaOrder__c": 0,
        "%vlocity_namespace%__GlobalKey__c": "accee435-5423-fab1-2a2f-763a55b70f31",
        "%vlocity_namespace%__InterfaceFieldAPIName__c": "Policy:AccountId",
        "%vlocity_namespace%__IsDisabled__c": false,
        "%vlocity_namespace%__IsRequiredForUpsert__c": false,
        "%vlocity_namespace%__LinkCreatedIndex__c": 0,
        "%vlocity_namespace%__MapId__c": "VPL-np-ReadPolicyDetail-100-1Custom716",
        "%vlocity_namespace%__OMplusSyncEnabled__c": false,
        "%vlocity_namespace%__UpsertKey__c": false,
        "Name": "port_ReadPolicyDetail_Card",
        "VlocityDataPackType": "SObject",
        "VlocityRecordSObjectType": "%vlocity_namespace%__DRMapItem__c"
    },
    {
        "%vlocity_namespace%__DomainObjectAPIName__c": "json",
        "%vlocity_namespace%__DomainObjectCreationOrder__c": 1,
        "%vlocity_namespace%__DomainObjectFieldAPIName__c": "Account:Name",
        "%vlocity_namespace%__FormulaOrder__c": 0,
        "%vlocity_namespace%__GlobalKey__c": "e6746d4e-9fdf-73eb-cdcf-996c256afcff",
        "%vlocity_namespace%__InterfaceFieldAPIName__c": "Policy:Policyholder:Name",
        "%vlocity_namespace%__IsDisabled__c": false,
        "%vlocity_namespace%__IsRequiredForUpsert__c": false,
        "%vlocity_namespace%__LinkCreatedIndex__c": 0,
        "%vlocity_namespace%__MapId__c": "VPL-np-ReadPolicyDetail-100-1Custom4624",
        "%vlocity_namespace%__OMplusSyncEnabled__c": false,
        "%vlocity_namespace%__UpsertKey__c": false,
        "Name": "port_ReadPolicyDetail_Card",
        "VlocityDataPackType": "SObject",
        "VlocityRecordSObjectType": "%vlocity_namespace%__DRMapItem__c"
    },
    {
        "%vlocity_namespace%__DomainObjectAPIName__c": "json",
        "%vlocity_namespace%__DomainObjectCreationOrder__c": 1,
        "%vlocity_namespace%__DomainObjectFieldAPIName__c": "Account:Phone",
        "%vlocity_namespace%__FormulaOrder__c": 0,
        "%vlocity_namespace%__GlobalKey__c": "01728585-a3a0-50c2-f307-d74db55c413a",
        "%vlocity_namespace%__InterfaceFieldAPIName__c": "Policy:Policyholder:Phone",
        "%vlocity_namespace%__IsDisabled__c": false,
        "%vlocity_namespace%__IsRequiredForUpsert__c": false,
        "%vlocity_namespace%__LinkCreatedIndex__c": 0,
        "%vlocity_namespace%__MapId__c": "VPL-np-ReadPolicyDetail-100-1Customa19f4000000chtuAAAItem18",
        "%vlocity_namespace%__OMplusSyncEnabled__c": false,
        "%vlocity_namespace%__UpsertKey__c": false,
        "Name": "port_ReadPolicyDetail_Card",
        "VlocityDataPackType": "SObject",
        "VlocityRecordSObjectType": "%vlocity_namespace%__DRMapItem__c"
    },
    {
        "%vlocity_namespace%__DomainObjectAPIName__c": "json",
        "%vlocity_namespace%__DomainObjectCreationOrder__c": 1,
        "%vlocity_namespace%__DomainObjectFieldAPIName__c": "Account:Policyholder",
        "%vlocity_namespace%__FormulaOrder__c": 0,
        "%vlocity_namespace%__GlobalKey__c": "cf356cc9-2d5d-427c-f547-b52813eef615",
        "%vlocity_namespace%__InterfaceFieldAPIName__c": "Policy:Policyholder:Name",
        "%vlocity_namespace%__IsDisabled__c": false,
        "%vlocity_namespace%__IsRequiredForUpsert__c": false,
        "%vlocity_namespace%__LinkCreatedIndex__c": 0,
        "%vlocity_namespace%__MapId__c": "VPL-np-ReadPolicyDetail-100-1Customa19f4000000chtuAAAItem17",
        "%vlocity_namespace%__OMplusSyncEnabled__c": false,
        "%vlocity_namespace%__UpsertKey__c": false,
        "Name": "port_ReadPolicyDetail_Card",
        "VlocityDataPackType": "SObject",
        "VlocityRecordSObjectType": "%vlocity_namespace%__DRMapItem__c"
    },
    {
        "%vlocity_namespace%__DomainObjectAPIName__c": "json",
        "%vlocity_namespace%__DomainObjectCreationOrder__c": 1,
        "%vlocity_namespace%__DomainObjectFieldAPIName__c": "AnnualPremium",
        "%vlocity_namespace%__FormulaOrder__c": 0,
        "%vlocity_namespace%__GlobalKey__c": "0b517634-55c8-295f-6762-b8958f69fd1e",
        "%vlocity_namespace%__InterfaceFieldAPIName__c": "Policy:%vlocity_namespace%__AnnualPremium__c",
        "%vlocity_namespace%__IsDisabled__c": false,
        "%vlocity_namespace%__IsRequiredForUpsert__c": false,
        "%vlocity_namespace%__LinkCreatedIndex__c": 0,
        "%vlocity_namespace%__MapId__c": "VPL-np-ReadPolicyDetail-100-1Customa19f4000000chtuAAAItem37",
        "%vlocity_namespace%__OMplusSyncEnabled__c": false,
        "%vlocity_namespace%__UpsertKey__c": false,
        "Name": "port_ReadPolicyDetail_Card",
        "VlocityDataPackType": "SObject",
        "VlocityRecordSObjectType": "%vlocity_namespace%__DRMapItem__c"
    },
    {
        "%vlocity_namespace%__DomainObjectAPIName__c": "json",
        "%vlocity_namespace%__DomainObjectCreationOrder__c": 1,
        "%vlocity_namespace%__DomainObjectFieldAPIName__c": "BenefitPlanId",
        "%vlocity_namespace%__FormulaOrder__c": 0,
        "%vlocity_namespace%__GlobalKey__c": "bcd9a852-9326-89f3-a7cf-f1ba7badbc32",
        "%vlocity_namespace%__InterfaceFieldAPIName__c": "Policy:%vlocity_namespace%__BenefitPlanId__c",
        "%vlocity_namespace%__IsDisabled__c": false,
        "%vlocity_namespace%__IsRequiredForUpsert__c": false,
        "%vlocity_namespace%__LinkCreatedIndex__c": 0,
        "%vlocity_namespace%__MapId__c": "VPL-np-ReadPolicyDetail-100-1Customa19f4000000chtuAAAItem38",
        "%vlocity_namespace%__OMplusSyncEnabled__c": false,
        "%vlocity_namespace%__UpsertKey__c": false,
        "Name": "port_ReadPolicyDetail_Card",
        "VlocityDataPackType": "SObject",
        "VlocityRecordSObjectType": "%vlocity_namespace%__DRMapItem__c"
    },
    {
        "%vlocity_namespace%__DomainObjectAPIName__c": "json",
        "%vlocity_namespace%__DomainObjectCreationOrder__c": 1,
        "%vlocity_namespace%__DomainObjectFieldAPIName__c": "Carrier:Id",
        "%vlocity_namespace%__FormulaOrder__c": 0,
        "%vlocity_namespace%__GlobalKey__c": "edfcba93-d6e2-8ce2-4b33-5bd4a9c84cc1",
        "%vlocity_namespace%__InterfaceFieldAPIName__c": "Policy:Carrier:Id",
        "%vlocity_namespace%__IsDisabled__c": false,
        "%vlocity_namespace%__IsRequiredForUpsert__c": false,
        "%vlocity_namespace%__LinkCreatedIndex__c": 0,
        "%vlocity_namespace%__MapId__c": "VPL-np-ReadPolicyDetail-100-1Customa19f4000000chtuAAAItem5",
        "%vlocity_namespace%__OMplusSyncEnabled__c": false,
        "%vlocity_namespace%__UpsertKey__c": false,
        "Name": "port_ReadPolicyDetail_Card",
        "VlocityDataPackType": "SObject",
        "VlocityRecordSObjectType": "%vlocity_namespace%__DRMapItem__c"
    },
    {
        "%vlocity_namespace%__DomainObjectAPIName__c": "json",
        "%vlocity_namespace%__DomainObjectCreationOrder__c": 1,
        "%vlocity_namespace%__DomainObjectFieldAPIName__c": "Carrier:Name",
        "%vlocity_namespace%__FormulaOrder__c": 0,
        "%vlocity_namespace%__GlobalKey__c": "b5465ff9-3261-98ca-9498-9411336e2956",
        "%vlocity_namespace%__InterfaceFieldAPIName__c": "Policy:Carrier:Name",
        "%vlocity_namespace%__IsDisabled__c": false,
        "%vlocity_namespace%__IsRequiredForUpsert__c": false,
        "%vlocity_namespace%__LinkCreatedIndex__c": 0,
        "%vlocity_namespace%__MapId__c": "VPL-np-ReadPolicyDetail-100-1Customa19f4000000chtuAAAItem6",
        "%vlocity_namespace%__OMplusSyncEnabled__c": false,
        "%vlocity_namespace%__UpsertKey__c": false,
        "Name": "port_ReadPolicyDetail_Card",
        "VlocityDataPackType": "SObject",
        "VlocityRecordSObjectType": "%vlocity_namespace%__DRMapItem__c"
    },
    {
        "%vlocity_namespace%__DomainObjectAPIName__c": "json",
        "%vlocity_namespace%__DomainObjectCreationOrder__c": 1,
        "%vlocity_namespace%__DomainObjectFieldAPIName__c": "CashSurrenderValue",
        "%vlocity_namespace%__FormulaOrder__c": 0,
        "%vlocity_namespace%__GlobalKey__c": "96fa0a8d-a8cf-30fa-6027-ed006e8df555",
        "%vlocity_namespace%__InterfaceFieldAPIName__c": "Policy:%vlocity_namespace%__CashSurrenderValue__c",
        "%vlocity_namespace%__IsDisabled__c": false,
        "%vlocity_namespace%__IsRequiredForUpsert__c": false,
        "%vlocity_namespace%__LinkCreatedIndex__c": 0,
        "%vlocity_namespace%__MapId__c": "VPL-np-ReadPolicyDetail-100-1Custom2245",
        "%vlocity_namespace%__OMplusSyncEnabled__c": false,
        "%vlocity_namespace%__UpsertKey__c": false,
        "Name": "port_ReadPolicyDetail_Card",
        "VlocityDataPackType": "SObject",
        "VlocityRecordSObjectType": "%vlocity_namespace%__DRMapItem__c"
    },
    {
        "%vlocity_namespace%__DomainObjectAPIName__c": "json",
        "%vlocity_namespace%__DomainObjectCreationOrder__c": 1,
        "%vlocity_namespace%__DomainObjectFieldAPIName__c": "CashValue",
        "%vlocity_namespace%__FormulaOrder__c": 0,
        "%vlocity_namespace%__GlobalKey__c": "1471ab16-0d96-159d-e5de-13dd5d0b2110",
        "%vlocity_namespace%__InterfaceFieldAPIName__c": "Policy:%vlocity_namespace%__CashValue__c",
        "%vlocity_namespace%__IsDisabled__c": false,
        "%vlocity_namespace%__IsRequiredForUpsert__c": false,
        "%vlocity_namespace%__LinkCreatedIndex__c": 0,
        "%vlocity_namespace%__MapId__c": "VPL-np-ReadPolicyDetail-100-1Customa19f4000000chtuAAAItem39",
        "%vlocity_namespace%__OMplusSyncEnabled__c": false,
        "%vlocity_namespace%__UpsertKey__c": false,
        "Name": "port_ReadPolicyDetail_Card",
        "VlocityDataPackType": "SObject",
        "VlocityRecordSObjectType": "%vlocity_namespace%__DRMapItem__c"
    },
    {
        "%vlocity_namespace%__DomainObjectAPIName__c": "json",
        "%vlocity_namespace%__DomainObjectCreationOrder__c": 1,
        "%vlocity_namespace%__DomainObjectFieldAPIName__c": "ContactId",
        "%vlocity_namespace%__FormulaOrder__c": 0,
        "%vlocity_namespace%__GlobalKey__c": "7d63a274-1b54-e4bb-9172-5c7df500604c",
        "%vlocity_namespace%__InterfaceFieldAPIName__c": "Policy:ContactId",
        "%vlocity_namespace%__IsDisabled__c": false,
        "%vlocity_namespace%__IsRequiredForUpsert__c": false,
        "%vlocity_namespace%__LinkCreatedIndex__c": 0,
        "%vlocity_namespace%__MapId__c": "VPL-np-ReadPolicyDetail-100-1Customa19f4000000chtuAAAItem7",
        "%vlocity_namespace%__OMplusSyncEnabled__c": false,
        "%vlocity_namespace%__UpsertKey__c": false,
        "Name": "port_ReadPolicyDetail_Card",
        "VlocityDataPackType": "SObject",
        "VlocityRecordSObjectType": "%vlocity_namespace%__DRMapItem__c"
    },
    {
        "%vlocity_namespace%__DomainObjectAPIName__c": "json",
        "%vlocity_namespace%__DomainObjectCreationOrder__c": 1,
        "%vlocity_namespace%__DomainObjectFieldAPIName__c": "DaysToExpire",
        "%vlocity_namespace%__FormulaOrder__c": 0,
        "%vlocity_namespace%__GlobalKey__c": "4f7cdaca-7a95-d248-8874-01be51e53570",
        "%vlocity_namespace%__InterfaceFieldAPIName__c": "Policy:%vlocity_namespace%__DaysToExpire__c",
        "%vlocity_namespace%__IsDisabled__c": false,
        "%vlocity_namespace%__IsRequiredForUpsert__c": false,
        "%vlocity_namespace%__LinkCreatedIndex__c": 0,
        "%vlocity_namespace%__MapId__c": "VPL-np-ReadPolicyDetail-100-1Customa19f4000000chtuAAAItem40",
        "%vlocity_namespace%__OMplusSyncEnabled__c": false,
        "%vlocity_namespace%__UpsertKey__c": false,
        "Name": "port_ReadPolicyDetail_Card",
        "VlocityDataPackType": "SObject",
        "VlocityRecordSObjectType": "%vlocity_namespace%__DRMapItem__c"
    },
    {
        "%vlocity_namespace%__DomainObjectAPIName__c": "json",
        "%vlocity_namespace%__DomainObjectCreationOrder__c": 1,
        "%vlocity_namespace%__DomainObjectFieldAPIName__c": "DeathBenefit",
        "%vlocity_namespace%__FormulaOrder__c": 0,
        "%vlocity_namespace%__GlobalKey__c": "5d16b686-9c98-5ccb-2167-626fc4df1d2a",
        "%vlocity_namespace%__InterfaceFieldAPIName__c": "Policy:%vlocity_namespace%__DeathBenefit__c",
        "%vlocity_namespace%__IsDisabled__c": false,
        "%vlocity_namespace%__IsRequiredForUpsert__c": false,
        "%vlocity_namespace%__LinkCreatedIndex__c": 0,
        "%vlocity_namespace%__MapId__c": "VPL-np-ReadPolicyDetail-100-1Custom6989",
        "%vlocity_namespace%__OMplusSyncEnabled__c": false,
        "%vlocity_namespace%__UpsertKey__c": false,
        "Name": "port_ReadPolicyDetail_Card",
        "VlocityDataPackType": "SObject",
        "VlocityRecordSObjectType": "%vlocity_namespace%__DRMapItem__c"
    },
    {
        "%vlocity_namespace%__DomainObjectAPIName__c": "json",
        "%vlocity_namespace%__DomainObjectCreationOrder__c": 1,
        "%vlocity_namespace%__DomainObjectFieldAPIName__c": "Description",
        "%vlocity_namespace%__FormulaOrder__c": 0,
        "%vlocity_namespace%__GlobalKey__c": "c28c8a22-1655-6287-c1f3-665b58928761",
        "%vlocity_namespace%__InterfaceFieldAPIName__c": "Policy:Description",
        "%vlocity_namespace%__IsDisabled__c": false,
        "%vlocity_namespace%__IsRequiredForUpsert__c": false,
        "%vlocity_namespace%__LinkCreatedIndex__c": 0,
        "%vlocity_namespace%__MapId__c": "VPL-np-ReadPolicyDetail-100-1Customa19f4000000chtuAAAItem8",
        "%vlocity_namespace%__OMplusSyncEnabled__c": false,
        "%vlocity_namespace%__UpsertKey__c": false,
        "Name": "port_ReadPolicyDetail_Card",
        "VlocityDataPackType": "SObject",
        "VlocityRecordSObjectType": "%vlocity_namespace%__DRMapItem__c"
    },
    {
        "%vlocity_namespace%__DomainObjectAPIName__c": "json",
        "%vlocity_namespace%__DomainObjectCreationOrder__c": 1,
        "%vlocity_namespace%__DomainObjectFieldAPIName__c": "EffectiveTerm",
        "%vlocity_namespace%__DomainObjectFieldType__c": "Date(MM/dd/YYYY)",
        "%vlocity_namespace%__FormulaOrder__c": 0,
        "%vlocity_namespace%__GlobalKey__c": "991a9e95-3ef8-4d1b-56ca-35e0d7cbb0b2",
        "%vlocity_namespace%__InterfaceFieldAPIName__c": "Policy:%vlocity_namespace%__EffectiveTerm__c",
        "%vlocity_namespace%__IsDisabled__c": false,
        "%vlocity_namespace%__IsRequiredForUpsert__c": false,
        "%vlocity_namespace%__LinkCreatedIndex__c": 0,
        "%vlocity_namespace%__MapId__c": "VPL-np-ReadPolicyDetail-100-1Custom6970",
        "%vlocity_namespace%__OMplusSyncEnabled__c": false,
        "%vlocity_namespace%__UpsertKey__c": false,
        "Name": "port_ReadPolicyDetail_Card",
        "VlocityDataPackType": "SObject",
        "VlocityRecordSObjectType": "%vlocity_namespace%__DRMapItem__c"
    },
    {
        "%vlocity_namespace%__DomainObjectAPIName__c": "json",
        "%vlocity_namespace%__DomainObjectCreationOrder__c": 1,
        "%vlocity_namespace%__DomainObjectFieldAPIName__c": "ExpirationDate",
        "%vlocity_namespace%__FormulaOrder__c": 0,
        "%vlocity_namespace%__GlobalKey__c": "914f69ca-f3a7-06a7-fabf-b7c392610412",
        "%vlocity_namespace%__InterfaceFieldAPIName__c": "Policy:%vlocity_namespace%__ExpirationDate__c",
        "%vlocity_namespace%__IsDisabled__c": false,
        "%vlocity_namespace%__IsRequiredForUpsert__c": false,
        "%vlocity_namespace%__LinkCreatedIndex__c": 0,
        "%vlocity_namespace%__MapId__c": "VPL-np-ReadPolicyDetail-100-1Customa19f4000000chtuAAAItem41",
        "%vlocity_namespace%__OMplusSyncEnabled__c": false,
        "%vlocity_namespace%__UpsertKey__c": false,
        "Name": "port_ReadPolicyDetail_Card",
        "VlocityDataPackType": "SObject",
        "VlocityRecordSObjectType": "%vlocity_namespace%__DRMapItem__c"
    },
    {
        "%vlocity_namespace%__DomainObjectAPIName__c": "json",
        "%vlocity_namespace%__DomainObjectCreationOrder__c": 1,
        "%vlocity_namespace%__DomainObjectFieldAPIName__c": "FaceAmount",
        "%vlocity_namespace%__FormulaOrder__c": 0,
        "%vlocity_namespace%__GlobalKey__c": "d51e738c-c592-da54-e8e1-98249acb10f3",
        "%vlocity_namespace%__InterfaceFieldAPIName__c": "Policy:%vlocity_namespace%__FaceAmount__c",
        "%vlocity_namespace%__IsDisabled__c": false,
        "%vlocity_namespace%__IsRequiredForUpsert__c": false,
        "%vlocity_namespace%__LinkCreatedIndex__c": 0,
        "%vlocity_namespace%__MapId__c": "VPL-np-ReadPolicyDetail-100-1Customa19f4000000chtuAAAItem42",
        "%vlocity_namespace%__OMplusSyncEnabled__c": false,
        "%vlocity_namespace%__UpsertKey__c": false,
        "Name": "port_ReadPolicyDetail_Card",
        "VlocityDataPackType": "SObject",
        "VlocityRecordSObjectType": "%vlocity_namespace%__DRMapItem__c"
    },
    {
        "%vlocity_namespace%__DomainObjectAPIName__c": "json",
        "%vlocity_namespace%__DomainObjectCreationOrder__c": 1,
        "%vlocity_namespace%__DomainObjectFieldAPIName__c": "GuaranteedDeathBenefit",
        "%vlocity_namespace%__FormulaOrder__c": 0,
        "%vlocity_namespace%__GlobalKey__c": "e140b090-6f16-f3c7-8cd3-51416515f801",
        "%vlocity_namespace%__InterfaceFieldAPIName__c": "Policy:%vlocity_namespace%__GuaranteedDeathBenefit__c",
        "%vlocity_namespace%__IsDisabled__c": false,
        "%vlocity_namespace%__IsRequiredForUpsert__c": false,
        "%vlocity_namespace%__LinkCreatedIndex__c": 0,
        "%vlocity_namespace%__MapId__c": "VPL-np-ReadPolicyDetail-100-1Custom6391",
        "%vlocity_namespace%__OMplusSyncEnabled__c": false,
        "%vlocity_namespace%__UpsertKey__c": false,
        "Name": "port_ReadPolicyDetail_Card",
        "VlocityDataPackType": "SObject",
        "VlocityRecordSObjectType": "%vlocity_namespace%__DRMapItem__c"
    },
    {
        "%vlocity_namespace%__DomainObjectAPIName__c": "json",
        "%vlocity_namespace%__DomainObjectCreationOrder__c": 1,
        "%vlocity_namespace%__DomainObjectFieldAPIName__c": "Id",
        "%vlocity_namespace%__FormulaOrder__c": 0,
        "%vlocity_namespace%__GlobalKey__c": "93b901e1-c441-fb0c-0b62-c485922ddcf0",
        "%vlocity_namespace%__InterfaceFieldAPIName__c": "Policy:Id",
        "%vlocity_namespace%__IsDisabled__c": false,
        "%vlocity_namespace%__IsRequiredForUpsert__c": false,
        "%vlocity_namespace%__LinkCreatedIndex__c": 0,
        "%vlocity_namespace%__MapId__c": "VPL-np-ReadPolicyDetail-100-1Customa19f4000000chtuAAAItem10",
        "%vlocity_namespace%__OMplusSyncEnabled__c": false,
        "%vlocity_namespace%__UpsertKey__c": false,
        "Name": "port_ReadPolicyDetail_Card",
        "VlocityDataPackType": "SObject",
        "VlocityRecordSObjectType": "%vlocity_namespace%__DRMapItem__c"
    },
    {
        "%vlocity_namespace%__DomainObjectAPIName__c": "json",
        "%vlocity_namespace%__DomainObjectCreationOrder__c": 1,
        "%vlocity_namespace%__DomainObjectFieldAPIName__c": "InceptionDate",
        "%vlocity_namespace%__FormulaOrder__c": 0,
        "%vlocity_namespace%__GlobalKey__c": "911f6b9e-4466-2610-1ee6-c04f5e293bda",
        "%vlocity_namespace%__InterfaceFieldAPIName__c": "Policy:%vlocity_namespace%__InceptionDate__c",
        "%vlocity_namespace%__IsDisabled__c": false,
        "%vlocity_namespace%__IsRequiredForUpsert__c": false,
        "%vlocity_namespace%__LinkCreatedIndex__c": 0,
        "%vlocity_namespace%__MapId__c": "VPL-np-ReadPolicyDetail-100-1Customa19f4000000chtuAAAItem43",
        "%vlocity_namespace%__OMplusSyncEnabled__c": false,
        "%vlocity_namespace%__UpsertKey__c": false,
        "Name": "port_ReadPolicyDetail_Card",
        "VlocityDataPackType": "SObject",
        "VlocityRecordSObjectType": "%vlocity_namespace%__DRMapItem__c"
    },
    {
        "%vlocity_namespace%__DomainObjectAPIName__c": "json",
        "%vlocity_namespace%__DomainObjectCreationOrder__c": 1,
        "%vlocity_namespace%__DomainObjectFieldAPIName__c": "InstallDate",
        "%vlocity_namespace%__FormulaOrder__c": 0,
        "%vlocity_namespace%__GlobalKey__c": "62e56714-7de0-98f2-b722-e327ed7c9f6d",
        "%vlocity_namespace%__InterfaceFieldAPIName__c": "Policy:InstallDate",
        "%vlocity_namespace%__IsDisabled__c": false,
        "%vlocity_namespace%__IsRequiredForUpsert__c": false,
        "%vlocity_namespace%__LinkCreatedIndex__c": 0,
        "%vlocity_namespace%__MapId__c": "VPL-np-ReadPolicyDetail-100-1Customa19f4000000chtuAAAItem11",
        "%vlocity_namespace%__OMplusSyncEnabled__c": false,
        "%vlocity_namespace%__UpsertKey__c": false,
        "Name": "port_ReadPolicyDetail_Card",
        "VlocityDataPackType": "SObject",
        "VlocityRecordSObjectType": "%vlocity_namespace%__DRMapItem__c"
    },
    {
        "%vlocity_namespace%__DomainObjectAPIName__c": "json",
        "%vlocity_namespace%__DomainObjectCreationOrder__c": 1,
        "%vlocity_namespace%__DomainObjectFieldAPIName__c": "LastModifiedDate",
        "%vlocity_namespace%__FormulaOrder__c": 0,
        "%vlocity_namespace%__GlobalKey__c": "2825f80f-bc44-47cb-9179-abccbea91dff",
        "%vlocity_namespace%__InterfaceFieldAPIName__c": "Policy:LastModifiedDate",
        "%vlocity_namespace%__IsDisabled__c": false,
        "%vlocity_namespace%__IsRequiredForUpsert__c": false,
        "%vlocity_namespace%__LinkCreatedIndex__c": 0,
        "%vlocity_namespace%__MapId__c": "VPL-np-ReadPolicyDetail-100-1Customa19f4000000chtuAAAItem20",
        "%vlocity_namespace%__OMplusSyncEnabled__c": false,
        "%vlocity_namespace%__UpsertKey__c": false,
        "Name": "port_ReadPolicyDetail_Card",
        "VlocityDataPackType": "SObject",
        "VlocityRecordSObjectType": "%vlocity_namespace%__DRMapItem__c"
    },
    {
        "%vlocity_namespace%__DomainObjectAPIName__c": "json",
        "%vlocity_namespace%__DomainObjectCreationOrder__c": 1,
        "%vlocity_namespace%__DomainObjectFieldAPIName__c": "LineOfBusiness",
        "%vlocity_namespace%__FormulaOrder__c": 0,
        "%vlocity_namespace%__GlobalKey__c": "90ee0819-c9d8-bd08-7923-1b87249bd3c5",
        "%vlocity_namespace%__InterfaceFieldAPIName__c": "Policy:%vlocity_namespace%__LineofBusiness__c",
        "%vlocity_namespace%__IsDisabled__c": false,
        "%vlocity_namespace%__IsRequiredForUpsert__c": false,
        "%vlocity_namespace%__LinkCreatedIndex__c": 0,
        "%vlocity_namespace%__MapId__c": "VPL-np-ReadPolicyDetail-100-1Customa19f4000000chtuAAAItem44",
        "%vlocity_namespace%__OMplusSyncEnabled__c": false,
        "%vlocity_namespace%__UpsertKey__c": false,
        "Name": "port_ReadPolicyDetail_Card",
        "VlocityDataPackType": "SObject",
        "VlocityRecordSObjectType": "%vlocity_namespace%__DRMapItem__c"
    },
    {
        "%vlocity_namespace%__DomainObjectAPIName__c": "json",
        "%vlocity_namespace%__DomainObjectCreationOrder__c": 1,
        "%vlocity_namespace%__DomainObjectFieldAPIName__c": "Name",
        "%vlocity_namespace%__FormulaOrder__c": 0,
        "%vlocity_namespace%__GlobalKey__c": "60e7c89c-cb63-21a5-72e3-831a4174eb07",
        "%vlocity_namespace%__InterfaceFieldAPIName__c": "Policy:Name",
        "%vlocity_namespace%__IsDisabled__c": false,
        "%vlocity_namespace%__IsRequiredForUpsert__c": false,
        "%vlocity_namespace%__LinkCreatedIndex__c": 0,
        "%vlocity_namespace%__MapId__c": "VPL-np-ReadPolicyDetail-100-1Customa19f4000000chtuAAAItem24",
        "%vlocity_namespace%__OMplusSyncEnabled__c": false,
        "%vlocity_namespace%__UpsertKey__c": false,
        "Name": "port_ReadPolicyDetail_Card",
        "VlocityDataPackType": "SObject",
        "VlocityRecordSObjectType": "%vlocity_namespace%__DRMapItem__c"
    },
    {
        "%vlocity_namespace%__DomainObjectAPIName__c": "json",
        "%vlocity_namespace%__DomainObjectCreationOrder__c": 1,
        "%vlocity_namespace%__DomainObjectFieldAPIName__c": "ParentId",
        "%vlocity_namespace%__FormulaOrder__c": 0,
        "%vlocity_namespace%__GlobalKey__c": "a208e733-18d9-a1b6-964e-80936d5a19ce",
        "%vlocity_namespace%__InterfaceFieldAPIName__c": "Policy:ParentId",
        "%vlocity_namespace%__IsDisabled__c": false,
        "%vlocity_namespace%__IsRequiredForUpsert__c": false,
        "%vlocity_namespace%__LinkCreatedIndex__c": 0,
        "%vlocity_namespace%__MapId__c": "VPL-np-ReadPolicyDetail-100-1Customa19f4000000chtuAAAItem25",
        "%vlocity_namespace%__OMplusSyncEnabled__c": false,
        "%vlocity_namespace%__UpsertKey__c": false,
        "Name": "port_ReadPolicyDetail_Card",
        "VlocityDataPackType": "SObject",
        "VlocityRecordSObjectType": "%vlocity_namespace%__DRMapItem__c"
    },
    {
        "%vlocity_namespace%__DomainObjectAPIName__c": "json",
        "%vlocity_namespace%__DomainObjectCreationOrder__c": 1,
        "%vlocity_namespace%__DomainObjectFieldAPIName__c": "PaymentMethod",
        "%vlocity_namespace%__FormulaOrder__c": 0,
        "%vlocity_namespace%__GlobalKey__c": "3c002f7e-c06b-2682-30f4-3c31930d1d93",
        "%vlocity_namespace%__InterfaceFieldAPIName__c": "Policy:%vlocity_namespace%__PaymentMethodId__c",
        "%vlocity_namespace%__IsDisabled__c": false,
        "%vlocity_namespace%__IsRequiredForUpsert__c": false,
        "%vlocity_namespace%__LinkCreatedIndex__c": 0,
        "%vlocity_namespace%__MapId__c": "VPL-np-ReadPolicyDetail-100-1Customa19f4000000chtuAAAItem45",
        "%vlocity_namespace%__OMplusSyncEnabled__c": false,
        "%vlocity_namespace%__UpsertKey__c": false,
        "Name": "port_ReadPolicyDetail_Card",
        "VlocityDataPackType": "SObject",
        "VlocityRecordSObjectType": "%vlocity_namespace%__DRMapItem__c"
    },
    {
        "%vlocity_namespace%__DomainObjectAPIName__c": "json",
        "%vlocity_namespace%__DomainObjectCreationOrder__c": 1,
        "%vlocity_namespace%__DomainObjectFieldAPIName__c": "Policy:City",
        "%vlocity_namespace%__FormulaOrder__c": 0,
        "%vlocity_namespace%__GlobalKey__c": "da73881c-7f7f-2056-4ac1-e5f515ca2772",
        "%vlocity_namespace%__InterfaceFieldAPIName__c": "Policy:Policyholder:BillingCity",
        "%vlocity_namespace%__IsDisabled__c": false,
        "%vlocity_namespace%__IsRequiredForUpsert__c": false,
        "%vlocity_namespace%__LinkCreatedIndex__c": 0,
        "%vlocity_namespace%__MapId__c": "VPL-np-ReadPolicyDetail-100-1Customa19f4000000chtuAAAItem13",
        "%vlocity_namespace%__OMplusSyncEnabled__c": false,
        "%vlocity_namespace%__UpsertKey__c": false,
        "Name": "port_ReadPolicyDetail_Card",
        "VlocityDataPackType": "SObject",
        "VlocityRecordSObjectType": "%vlocity_namespace%__DRMapItem__c"
    },
    {
        "%vlocity_namespace%__DomainObjectAPIName__c": "json",
        "%vlocity_namespace%__DomainObjectCreationOrder__c": 1,
        "%vlocity_namespace%__DomainObjectFieldAPIName__c": "Policy:PostalCode",
        "%vlocity_namespace%__FormulaOrder__c": 0,
        "%vlocity_namespace%__GlobalKey__c": "25c19ac9-e21a-4cb2-a5cd-d8258be0b51b",
        "%vlocity_namespace%__InterfaceFieldAPIName__c": "Policy:Policyholder:BillingPostalCode",
        "%vlocity_namespace%__IsDisabled__c": false,
        "%vlocity_namespace%__IsRequiredForUpsert__c": false,
        "%vlocity_namespace%__LinkCreatedIndex__c": 0,
        "%vlocity_namespace%__MapId__c": "VPL-np-ReadPolicyDetail-100-1Customa19f4000000chtuAAAItem14",
        "%vlocity_namespace%__OMplusSyncEnabled__c": false,
        "%vlocity_namespace%__UpsertKey__c": false,
        "Name": "port_ReadPolicyDetail_Card",
        "VlocityDataPackType": "SObject",
        "VlocityRecordSObjectType": "%vlocity_namespace%__DRMapItem__c"
    },
    {
        "%vlocity_namespace%__DomainObjectAPIName__c": "json",
        "%vlocity_namespace%__DomainObjectCreationOrder__c": 1,
        "%vlocity_namespace%__DomainObjectFieldAPIName__c": "Policy:State",
        "%vlocity_namespace%__FormulaOrder__c": 0,
        "%vlocity_namespace%__GlobalKey__c": "3b39ef8d-f5f4-f562-9f49-645f24470a5f",
        "%vlocity_namespace%__InterfaceFieldAPIName__c": "Policy:Policyholder:BillingState",
        "%vlocity_namespace%__IsDisabled__c": false,
        "%vlocity_namespace%__IsRequiredForUpsert__c": false,
        "%vlocity_namespace%__LinkCreatedIndex__c": 0,
        "%vlocity_namespace%__MapId__c": "VPL-np-ReadPolicyDetail-100-1Customa19f4000000chtuAAAItem15",
        "%vlocity_namespace%__OMplusSyncEnabled__c": false,
        "%vlocity_namespace%__UpsertKey__c": false,
        "Name": "port_ReadPolicyDetail_Card",
        "VlocityDataPackType": "SObject",
        "VlocityRecordSObjectType": "%vlocity_namespace%__DRMapItem__c"
    },
    {
        "%vlocity_namespace%__DomainObjectAPIName__c": "json",
        "%vlocity_namespace%__DomainObjectCreationOrder__c": 1,
        "%vlocity_namespace%__DomainObjectFieldAPIName__c": "Policy:Street",
        "%vlocity_namespace%__FormulaOrder__c": 0,
        "%vlocity_namespace%__GlobalKey__c": "69bb2691-f515-c519-1141-a689f1cc5a69",
        "%vlocity_namespace%__InterfaceFieldAPIName__c": "Policy:Policyholder:BillingStreet",
        "%vlocity_namespace%__IsDisabled__c": false,
        "%vlocity_namespace%__IsRequiredForUpsert__c": false,
        "%vlocity_namespace%__LinkCreatedIndex__c": 0,
        "%vlocity_namespace%__MapId__c": "VPL-np-ReadPolicyDetail-100-1Customa19f4000000chtuAAAItem16",
        "%vlocity_namespace%__OMplusSyncEnabled__c": false,
        "%vlocity_namespace%__UpsertKey__c": false,
        "Name": "port_ReadPolicyDetail_Card",
        "VlocityDataPackType": "SObject",
        "VlocityRecordSObjectType": "%vlocity_namespace%__DRMapItem__c"
    },
    {
        "%vlocity_namespace%__DomainObjectAPIName__c": "json",
        "%vlocity_namespace%__DomainObjectCreationOrder__c": 1,
        "%vlocity_namespace%__DomainObjectFieldAPIName__c": "PolicyAssetId",
        "%vlocity_namespace%__FormulaOrder__c": 0,
        "%vlocity_namespace%__GlobalKey__c": "acb61672-aea0-4249-b3ce-7a3943675ab1",
        "%vlocity_namespace%__InterfaceFieldAPIName__c": "Policy:%vlocity_namespace%__PolicyAssetId__c",
        "%vlocity_namespace%__IsDisabled__c": false,
        "%vlocity_namespace%__IsRequiredForUpsert__c": false,
        "%vlocity_namespace%__LinkCreatedIndex__c": 0,
        "%vlocity_namespace%__MapId__c": "VPL-np-ReadPolicyDetail-100-1Customa19f4000000chtuAAAItem46",
        "%vlocity_namespace%__OMplusSyncEnabled__c": false,
        "%vlocity_namespace%__UpsertKey__c": false,
        "Name": "port_ReadPolicyDetail_Card",
        "VlocityDataPackType": "SObject",
        "VlocityRecordSObjectType": "%vlocity_namespace%__DRMapItem__c"
    },
    {
        "%vlocity_namespace%__DomainObjectAPIName__c": "json",
        "%vlocity_namespace%__DomainObjectCreationOrder__c": 1,
        "%vlocity_namespace%__DomainObjectFieldAPIName__c": "PolicyAssetId",
        "%vlocity_namespace%__FormulaOrder__c": 0,
        "%vlocity_namespace%__GlobalKey__c": "1f602d03-d1cd-e9f6-b17d-daee7e45cb3b",
        "%vlocity_namespace%__InterfaceFieldAPIName__c": "Policy:PolicyAssetId",
        "%vlocity_namespace%__IsDisabled__c": false,
        "%vlocity_namespace%__IsRequiredForUpsert__c": false,
        "%vlocity_namespace%__LinkCreatedIndex__c": 0,
        "%vlocity_namespace%__MapId__c": "VPL-np-ReadPolicyDetail-100-1Customa19f4000000chtuAAAItem26",
        "%vlocity_namespace%__OMplusSyncEnabled__c": false,
        "%vlocity_namespace%__UpsertKey__c": false,
        "Name": "port_ReadPolicyDetail_Card",
        "VlocityDataPackType": "SObject",
        "VlocityRecordSObjectType": "%vlocity_namespace%__DRMapItem__c"
    },
    {
        "%vlocity_namespace%__DomainObjectAPIName__c": "json",
        "%vlocity_namespace%__DomainObjectCreationOrder__c": 1,
        "%vlocity_namespace%__DomainObjectFieldAPIName__c": "PolicyId",
        "%vlocity_namespace%__FormulaOrder__c": 0,
        "%vlocity_namespace%__GlobalKey__c": "2c373dc0-bd7e-da1c-55ed-d6dd993bf076",
        "%vlocity_namespace%__InterfaceFieldAPIName__c": "Policy:Id",
        "%vlocity_namespace%__IsDisabled__c": false,
        "%vlocity_namespace%__IsRequiredForUpsert__c": false,
        "%vlocity_namespace%__LinkCreatedIndex__c": 0,
        "%vlocity_namespace%__MapId__c": "VPL-np-ReadPolicyDetail-100-1Customa19f4000000chtuAAAItem9",
        "%vlocity_namespace%__OMplusSyncEnabled__c": false,
        "%vlocity_namespace%__UpsertKey__c": false,
        "Name": "port_ReadPolicyDetail_Card",
        "VlocityDataPackType": "SObject",
        "VlocityRecordSObjectType": "%vlocity_namespace%__DRMapItem__c"
    },
    {
        "%vlocity_namespace%__DomainObjectAPIName__c": "json",
        "%vlocity_namespace%__DomainObjectCreationOrder__c": 1,
        "%vlocity_namespace%__DomainObjectFieldAPIName__c": "PolicyName",
        "%vlocity_namespace%__FormulaOrder__c": 0,
        "%vlocity_namespace%__GlobalKey__c": "12d1fa0e-90b5-f765-9d23-4b26efe9405a",
        "%vlocity_namespace%__InterfaceFieldAPIName__c": "Policy:Name",
        "%vlocity_namespace%__IsDisabled__c": false,
        "%vlocity_namespace%__IsRequiredForUpsert__c": false,
        "%vlocity_namespace%__LinkCreatedIndex__c": 0,
        "%vlocity_namespace%__MapId__c": "VPL-np-ReadPolicyDetail-100-1Customa19f4000000chtuAAAItem23",
        "%vlocity_namespace%__OMplusSyncEnabled__c": false,
        "%vlocity_namespace%__UpsertKey__c": false,
        "Name": "port_ReadPolicyDetail_Card",
        "VlocityDataPackType": "SObject",
        "VlocityRecordSObjectType": "%vlocity_namespace%__DRMapItem__c"
    },
    {
        "%vlocity_namespace%__DomainObjectAPIName__c": "json",
        "%vlocity_namespace%__DomainObjectCreationOrder__c": 1,
        "%vlocity_namespace%__DomainObjectFieldAPIName__c": "PolicyNumber",
        "%vlocity_namespace%__FormulaOrder__c": 0,
        "%vlocity_namespace%__GlobalKey__c": "e09ed315-28f1-3da3-f803-ab9bb200eca0",
        "%vlocity_namespace%__InterfaceFieldAPIName__c": "Policy:SerialNumber",
        "%vlocity_namespace%__IsDisabled__c": false,
        "%vlocity_namespace%__IsRequiredForUpsert__c": false,
        "%vlocity_namespace%__LinkCreatedIndex__c": 0,
        "%vlocity_namespace%__MapId__c": "VPL-np-ReadPolicyDetail-100-1Customa19f4000000chtuAAAItem34",
        "%vlocity_namespace%__OMplusSyncEnabled__c": false,
        "%vlocity_namespace%__UpsertKey__c": false,
        "Name": "port_ReadPolicyDetail_Card",
        "VlocityDataPackType": "SObject",
        "VlocityRecordSObjectType": "%vlocity_namespace%__DRMapItem__c"
    },
    {
        "%vlocity_namespace%__DomainObjectAPIName__c": "json",
        "%vlocity_namespace%__DomainObjectCreationOrder__c": 1,
        "%vlocity_namespace%__DomainObjectFieldAPIName__c": "Policyholder",
        "%vlocity_namespace%__FormulaOrder__c": 0,
        "%vlocity_namespace%__GlobalKey__c": "1919d29f-cbe4-8f0e-988e-6bc322c7e435",
        "%vlocity_namespace%__InterfaceFieldAPIName__c": "Policy:Policyholder:Name",
        "%vlocity_namespace%__IsDisabled__c": false,
        "%vlocity_namespace%__IsRequiredForUpsert__c": false,
        "%vlocity_namespace%__LinkCreatedIndex__c": 0,
        "%vlocity_namespace%__MapId__c": "VPL-np-ReadPolicyDetail-100-1Customa19f4000000chtuAAAItem27",
        "%vlocity_namespace%__OMplusSyncEnabled__c": false,
        "%vlocity_namespace%__UpsertKey__c": false,
        "Name": "port_ReadPolicyDetail_Card",
        "VlocityDataPackType": "SObject",
        "VlocityRecordSObjectType": "%vlocity_namespace%__DRMapItem__c"
    },
    {
        "%vlocity_namespace%__DomainObjectAPIName__c": "json",
        "%vlocity_namespace%__DomainObjectCreationOrder__c": 1,
        "%vlocity_namespace%__DomainObjectFieldAPIName__c": "PrimaryProducerId:Id",
        "%vlocity_namespace%__FormulaOrder__c": 0,
        "%vlocity_namespace%__GlobalKey__c": "f4664e0d-44ed-6534-ac17-9efe29c31af3",
        "%vlocity_namespace%__InterfaceFieldAPIName__c": "Policy:PrimaryProducerId:Id",
        "%vlocity_namespace%__IsDisabled__c": false,
        "%vlocity_namespace%__IsRequiredForUpsert__c": false,
        "%vlocity_namespace%__LinkCreatedIndex__c": 0,
        "%vlocity_namespace%__MapId__c": "VPL-np-ReadPolicyDetail-100-1Custom1181",
        "%vlocity_namespace%__OMplusSyncEnabled__c": false,
        "%vlocity_namespace%__UpsertKey__c": false,
        "Name": "port_ReadPolicyDetail_Card",
        "VlocityDataPackType": "SObject",
        "VlocityRecordSObjectType": "%vlocity_namespace%__DRMapItem__c"
    },
    {
        "%vlocity_namespace%__DomainObjectAPIName__c": "json",
        "%vlocity_namespace%__DomainObjectCreationOrder__c": 1,
        "%vlocity_namespace%__DomainObjectFieldAPIName__c": "PrimaryProducerId:Name",
        "%vlocity_namespace%__FormulaOrder__c": 0,
        "%vlocity_namespace%__GlobalKey__c": "227afc35-7104-7345-60ca-b995386b2f78",
        "%vlocity_namespace%__InterfaceFieldAPIName__c": "Policy:PrimaryProducerId:Name",
        "%vlocity_namespace%__IsDisabled__c": false,
        "%vlocity_namespace%__IsRequiredForUpsert__c": false,
        "%vlocity_namespace%__LinkCreatedIndex__c": 0,
        "%vlocity_namespace%__MapId__c": "VPL-np-ReadPolicyDetail-100-1Customa19f4000000chtuAAAItem28",
        "%vlocity_namespace%__OMplusSyncEnabled__c": false,
        "%vlocity_namespace%__UpsertKey__c": false,
        "Name": "port_ReadPolicyDetail_Card",
        "VlocityDataPackType": "SObject",
        "VlocityRecordSObjectType": "%vlocity_namespace%__DRMapItem__c"
    },
    {
        "%vlocity_namespace%__DomainObjectAPIName__c": "json",
        "%vlocity_namespace%__DomainObjectCreationOrder__c": 1,
        "%vlocity_namespace%__DomainObjectFieldAPIName__c": "Product2Id",
        "%vlocity_namespace%__FormulaOrder__c": 0,
        "%vlocity_namespace%__GlobalKey__c": "d682a735-ddab-cf62-f260-5e852fd225bb",
        "%vlocity_namespace%__InterfaceFieldAPIName__c": "Policy:Product2Id",
        "%vlocity_namespace%__IsDisabled__c": false,
        "%vlocity_namespace%__IsRequiredForUpsert__c": false,
        "%vlocity_namespace%__LinkCreatedIndex__c": 0,
        "%vlocity_namespace%__MapId__c": "VPL-np-ReadPolicyDetail-100-1Customa19f4000000chtuAAAItem29",
        "%vlocity_namespace%__OMplusSyncEnabled__c": false,
        "%vlocity_namespace%__UpsertKey__c": false,
        "Name": "port_ReadPolicyDetail_Card",
        "VlocityDataPackType": "SObject",
        "VlocityRecordSObjectType": "%vlocity_namespace%__DRMapItem__c"
    },
    {
        "%vlocity_namespace%__DomainObjectAPIName__c": "json",
        "%vlocity_namespace%__DomainObjectCreationOrder__c": 1,
        "%vlocity_namespace%__DomainObjectFieldAPIName__c": "PurchaseDate",
        "%vlocity_namespace%__FormulaOrder__c": 0,
        "%vlocity_namespace%__GlobalKey__c": "b9de379a-0f00-ce7b-6b7c-8603372eb3fe",
        "%vlocity_namespace%__InterfaceFieldAPIName__c": "Policy:PurchaseDate",
        "%vlocity_namespace%__IsDisabled__c": false,
        "%vlocity_namespace%__IsRequiredForUpsert__c": false,
        "%vlocity_namespace%__LinkCreatedIndex__c": 0,
        "%vlocity_namespace%__MapId__c": "VPL-np-ReadPolicyDetail-100-1Customa19f4000000chtuAAAItem30",
        "%vlocity_namespace%__OMplusSyncEnabled__c": false,
        "%vlocity_namespace%__UpsertKey__c": false,
        "Name": "port_ReadPolicyDetail_Card",
        "VlocityDataPackType": "SObject",
        "VlocityRecordSObjectType": "%vlocity_namespace%__DRMapItem__c"
    },
    {
        "%vlocity_namespace%__DomainObjectAPIName__c": "json",
        "%vlocity_namespace%__DomainObjectCreationOrder__c": 1,
        "%vlocity_namespace%__DomainObjectFieldAPIName__c": "Quantity",
        "%vlocity_namespace%__FormulaOrder__c": 0,
        "%vlocity_namespace%__GlobalKey__c": "d293f25f-a6e9-eee3-d4ff-051e716fc728",
        "%vlocity_namespace%__InterfaceFieldAPIName__c": "Policy:Quantity",
        "%vlocity_namespace%__IsDisabled__c": false,
        "%vlocity_namespace%__IsRequiredForUpsert__c": false,
        "%vlocity_namespace%__LinkCreatedIndex__c": 0,
        "%vlocity_namespace%__MapId__c": "VPL-np-ReadPolicyDetail-100-1Customa19f4000000chtuAAAItem31",
        "%vlocity_namespace%__OMplusSyncEnabled__c": false,
        "%vlocity_namespace%__UpsertKey__c": false,
        "Name": "port_ReadPolicyDetail_Card",
        "VlocityDataPackType": "SObject",
        "VlocityRecordSObjectType": "%vlocity_namespace%__DRMapItem__c"
    },
    {
        "%vlocity_namespace%__DomainObjectAPIName__c": "json",
        "%vlocity_namespace%__DomainObjectCreationOrder__c": 1,
        "%vlocity_namespace%__DomainObjectFieldAPIName__c": "RecordTypeId",
        "%vlocity_namespace%__FormulaOrder__c": 0,
        "%vlocity_namespace%__GlobalKey__c": "caafe57b-4c38-f076-a55b-e235a302ca71",
        "%vlocity_namespace%__InterfaceFieldAPIName__c": "Policy:RecordTypeId",
        "%vlocity_namespace%__IsDisabled__c": false,
        "%vlocity_namespace%__IsRequiredForUpsert__c": false,
        "%vlocity_namespace%__LinkCreatedIndex__c": 0,
        "%vlocity_namespace%__MapId__c": "VPL-np-ReadPolicyDetail-100-1Customa19f4000000chtuAAAItem32",
        "%vlocity_namespace%__OMplusSyncEnabled__c": false,
        "%vlocity_namespace%__UpsertKey__c": false,
        "Name": "port_ReadPolicyDetail_Card",
        "VlocityDataPackType": "SObject",
        "VlocityRecordSObjectType": "%vlocity_namespace%__DRMapItem__c"
    },
    {
        "%vlocity_namespace%__DomainObjectAPIName__c": "json",
        "%vlocity_namespace%__DomainObjectCreationOrder__c": 1,
        "%vlocity_namespace%__DomainObjectFieldAPIName__c": "RootAssetId",
        "%vlocity_namespace%__FormulaOrder__c": 0,
        "%vlocity_namespace%__GlobalKey__c": "de9f22ce-d015-5453-ef28-3fc7bc9679c7",
        "%vlocity_namespace%__InterfaceFieldAPIName__c": "Policy:RootAssetId",
        "%vlocity_namespace%__IsDisabled__c": false,
        "%vlocity_namespace%__IsRequiredForUpsert__c": false,
        "%vlocity_namespace%__LinkCreatedIndex__c": 0,
        "%vlocity_namespace%__MapId__c": "VPL-np-ReadPolicyDetail-100-1Customa19f4000000chtuAAAItem33",
        "%vlocity_namespace%__OMplusSyncEnabled__c": false,
        "%vlocity_namespace%__UpsertKey__c": false,
        "Name": "port_ReadPolicyDetail_Card",
        "VlocityDataPackType": "SObject",
        "VlocityRecordSObjectType": "%vlocity_namespace%__DRMapItem__c"
    },
    {
        "%vlocity_namespace%__DomainObjectAPIName__c": "json",
        "%vlocity_namespace%__DomainObjectCreationOrder__c": 1,
        "%vlocity_namespace%__DomainObjectFieldAPIName__c": "Status",
        "%vlocity_namespace%__FormulaOrder__c": 0,
        "%vlocity_namespace%__GlobalKey__c": "60021997-f7b2-2d0a-4084-7d76c571e17a",
        "%vlocity_namespace%__InterfaceFieldAPIName__c": "Policy:Status",
        "%vlocity_namespace%__IsDisabled__c": false,
        "%vlocity_namespace%__IsRequiredForUpsert__c": false,
        "%vlocity_namespace%__LinkCreatedIndex__c": 0,
        "%vlocity_namespace%__MapId__c": "VPL-np-ReadPolicyDetail-100-1Customa19f4000000chtuAAAItem35",
        "%vlocity_namespace%__OMplusSyncEnabled__c": false,
        "%vlocity_namespace%__UpsertKey__c": false,
        "Name": "port_ReadPolicyDetail_Card",
        "VlocityDataPackType": "SObject",
        "VlocityRecordSObjectType": "%vlocity_namespace%__DRMapItem__c"
    },
    {
        "%vlocity_namespace%__DomainObjectAPIName__c": "json",
        "%vlocity_namespace%__DomainObjectCreationOrder__c": 1,
        "%vlocity_namespace%__DomainObjectFieldAPIName__c": "Term",
        "%vlocity_namespace%__FormulaOrder__c": 0,
        "%vlocity_namespace%__GlobalKey__c": "d69cd28f-da53-6d8f-0f0a-3b8d0f104cd6",
        "%vlocity_namespace%__InterfaceFieldAPIName__c": "Policy:%vlocity_namespace%__Term__c",
        "%vlocity_namespace%__IsDisabled__c": false,
        "%vlocity_namespace%__IsRequiredForUpsert__c": false,
        "%vlocity_namespace%__LinkCreatedIndex__c": 0,
        "%vlocity_namespace%__MapId__c": "VPL-np-ReadPolicyDetail-100-1Customa19f4000000chtuAAAItem47",
        "%vlocity_namespace%__OMplusSyncEnabled__c": false,
        "%vlocity_namespace%__UpsertKey__c": false,
        "Name": "port_ReadPolicyDetail_Card",
        "VlocityDataPackType": "SObject",
        "VlocityRecordSObjectType": "%vlocity_namespace%__DRMapItem__c"
    },
    {
        "%vlocity_namespace%__DomainObjectAPIName__c": "json",
        "%vlocity_namespace%__DomainObjectCreationOrder__c": 1,
        "%vlocity_namespace%__DomainObjectFieldAPIName__c": "TotalPremiumForTerm",
        "%vlocity_namespace%__FormulaOrder__c": 0,
        "%vlocity_namespace%__GlobalKey__c": "bef33c57-55f9-7d84-fad7-5ddd882b50d6",
        "%vlocity_namespace%__InterfaceFieldAPIName__c": "Policy:%vlocity_namespace%__TotalPremiumForTerm__c",
        "%vlocity_namespace%__IsDisabled__c": false,
        "%vlocity_namespace%__IsRequiredForUpsert__c": false,
        "%vlocity_namespace%__LinkCreatedIndex__c": 0,
        "%vlocity_namespace%__MapId__c": "VPL-np-ReadPolicyDetail-100-1Customa19f4000000chtuAAAItem48",
        "%vlocity_namespace%__OMplusSyncEnabled__c": false,
        "%vlocity_namespace%__UpsertKey__c": false,
        "Name": "port_ReadPolicyDetail_Card",
        "VlocityDataPackType": "SObject",
        "VlocityRecordSObjectType": "%vlocity_namespace%__DRMapItem__c"
    },
    {
        "%vlocity_namespace%__DomainObjectAPIName__c": "json",
        "%vlocity_namespace%__DomainObjectCreationOrder__c": 1,
        "%vlocity_namespace%__DomainObjectFieldAPIName__c": "TotalValue",
        "%vlocity_namespace%__FormulaOrder__c": 0,
        "%vlocity_namespace%__GlobalKey__c": "158e02d7-1e21-73a4-f5b2-f356698f1fcd",
        "%vlocity_namespace%__InterfaceFieldAPIName__c": "Policy:%vlocity_namespace%__TotalValue__c",
        "%vlocity_namespace%__IsDisabled__c": false,
        "%vlocity_namespace%__IsRequiredForUpsert__c": false,
        "%vlocity_namespace%__LinkCreatedIndex__c": 0,
        "%vlocity_namespace%__MapId__c": "VPL-np-ReadPolicyDetail-100-1Customa19f4000000chtuAAAItem49",
        "%vlocity_namespace%__OMplusSyncEnabled__c": false,
        "%vlocity_namespace%__UpsertKey__c": false,
        "Name": "port_ReadPolicyDetail_Card",
        "VlocityDataPackType": "SObject",
        "VlocityRecordSObjectType": "%vlocity_namespace%__DRMapItem__c"
    },
    {
        "%vlocity_namespace%__DomainObjectAPIName__c": "json",
        "%vlocity_namespace%__DomainObjectCreationOrder__c": 1,
        "%vlocity_namespace%__DomainObjectFieldAPIName__c": "Type",
        "%vlocity_namespace%__FormulaOrder__c": 0,
        "%vlocity_namespace%__GlobalKey__c": "3b5491d5-f4b9-8e19-2b8d-43b9aef32435",
        "%vlocity_namespace%__InterfaceFieldAPIName__c": "Policy:%vlocity_namespace%__Type__c",
        "%vlocity_namespace%__IsDisabled__c": false,
        "%vlocity_namespace%__IsRequiredForUpsert__c": false,
        "%vlocity_namespace%__LinkCreatedIndex__c": 0,
        "%vlocity_namespace%__MapId__c": "VPL-np-ReadPolicyDetail-100-1Customa19f4000000chtuAAAItem50",
        "%vlocity_namespace%__OMplusSyncEnabled__c": false,
        "%vlocity_namespace%__UpsertKey__c": false,
        "Name": "port_ReadPolicyDetail_Card",
        "VlocityDataPackType": "SObject",
        "VlocityRecordSObjectType": "%vlocity_namespace%__DRMapItem__c"
    },
    {
        "%vlocity_namespace%__DomainObjectAPIName__c": "json",
        "%vlocity_namespace%__DomainObjectCreationOrder__c": 1,
        "%vlocity_namespace%__DomainObjectFieldAPIName__c": "UsageEndDate",
        "%vlocity_namespace%__FormulaOrder__c": 0,
        "%vlocity_namespace%__GlobalKey__c": "115f63f9-f016-61f0-f6b0-552c2b7225de",
        "%vlocity_namespace%__InterfaceFieldAPIName__c": "Policy:UsageEndDate",
        "%vlocity_namespace%__IsDisabled__c": false,
        "%vlocity_namespace%__IsRequiredForUpsert__c": false,
        "%vlocity_namespace%__LinkCreatedIndex__c": 0,
        "%vlocity_namespace%__MapId__c": "VPL-np-ReadPolicyDetail-100-1Customa19f4000000chtuAAAItem36",
        "%vlocity_namespace%__OMplusSyncEnabled__c": false,
        "%vlocity_namespace%__UpsertKey__c": false,
        "Name": "port_ReadPolicyDetail_Card",
        "VlocityDataPackType": "SObject",
        "VlocityRecordSObjectType": "%vlocity_namespace%__DRMapItem__c"
    }
]