{
    "%vlocity_namespace%__Description__c": "",
    "%vlocity_namespace%__EffectiveFromDate__c": "",
    "%vlocity_namespace%__EffectiveUntilDate__c": "",
    "%vlocity_namespace%__GlobalKey__c": "d2bca9c3-fcb7-ab6b-fa63-19ec4973776d",
    "%vlocity_namespace%__IsActive__c": true,
    "%vlocity_namespace%__IsDefault__c": false,
    "%vlocity_namespace%__ObjectClassId__c": {
        "%vlocity_namespace%__GlobalKey__c": "63ba6ae5f8c257f7cdccc385d2a85dca",
        "VlocityDataPackType": "VlocityLookupMatchingKeyObject",
        "VlocityLookupRecordSourceKey": "%vlocity_namespace%__ObjectClass__c/63ba6ae5f8c257f7cdccc385d2a85dca",
        "VlocityRecordSObjectType": "%vlocity_namespace%__ObjectClass__c"
    },
    "%vlocity_namespace%__ObjectFacet__c": [
        {
            "%vlocity_namespace%__EffectiveFromDate__c": "",
            "%vlocity_namespace%__EffectiveUntilDate__c": "",
            "%vlocity_namespace%__FacetId__c": {
                "%vlocity_namespace%__GlobalKey__c": "5ceff4783b0f59f31b27417a7064a12c",
                "VlocityDataPackType": "VlocityLookupMatchingKeyObject",
                "VlocityLookupRecordSourceKey": "%vlocity_namespace%__UIFacet__c/5ceff4783b0f59f31b27417a7064a12c",
                "VlocityRecordSObjectType": "%vlocity_namespace%__UIFacet__c"
            },
            "%vlocity_namespace%__GlobalKey__c": "855200d0-0f02-bfb2-e5a4-262408d41124",
            "%vlocity_namespace%__IsActive__c": true,
            "%vlocity_namespace%__ObjectLayoutId__c": {
                "%vlocity_namespace%__GlobalKey__c": "d2bca9c3-fcb7-ab6b-fa63-19ec4973776d",
                "VlocityDataPackType": "VlocityMatchingKeyObject",
                "VlocityMatchingRecordSourceKey": "%vlocity_namespace%__ObjectLayout__c/d2bca9c3-fcb7-ab6b-fa63-19ec4973776d",
                "VlocityRecordSObjectType": "%vlocity_namespace%__ObjectLayout__c"
            },
            "%vlocity_namespace%__ObjectSection__c": [
                {
                    "%vlocity_namespace%__ColumnLayout__c": "",
                    "%vlocity_namespace%__EffectiveFromDate__c": "",
                    "%vlocity_namespace%__EffectiveUntilDate__c": "",
                    "%vlocity_namespace%__GlobalKey__c": "1e859e2b-87de-6bad-e830-e589072bda88",
                    "%vlocity_namespace%__IsActive__c": true,
                    "%vlocity_namespace%__ObjectElement__c": [
                        {
                            "%vlocity_namespace%__AttributeId__c": "",
                            "%vlocity_namespace%__Column__c": "1",
                            "%vlocity_namespace%__EffectiveFromDate__c": "",
                            "%vlocity_namespace%__EffectiveUntilDate__c": "",
                            "%vlocity_namespace%__FieldApiName__c": "Name",
                            "%vlocity_namespace%__GlobalKey__c": "acc93d93-90aa-72d8-a22a-e81b4d58ffcb",
                            "%vlocity_namespace%__IsActive__c": true,
                            "%vlocity_namespace%__IsRequired__c": true,
                            "%vlocity_namespace%__ObjectSectionId__c": {
                                "Name": "1e859e2b-87de-6bad-e830-e589072bda88",
                                "VlocityDataPackType": "VlocityMatchingKeyObject",
                                "VlocityMatchingRecordSourceKey": "%vlocity_namespace%__ObjectSection__c/1e859e2b-87de-6bad-e830-e589072bda88",
                                "VlocityRecordSObjectType": "%vlocity_namespace%__ObjectSection__c"
                            },
                            "%vlocity_namespace%__Sequence__c": 1,
                            "%vlocity_namespace%__Type__c": "Field",
                            "Name": "Name",
                            "VlocityDataPackType": "SObject",
                            "VlocityRecordSObjectType": "%vlocity_namespace%__ObjectElement__c",
                            "VlocityRecordSourceKey": "%vlocity_namespace%__ObjectElement__c/acc93d93-90aa-72d8-a22a-e81b4d58ffcb"
                        },
                        {
                            "%vlocity_namespace%__AttributeId__c": "",
                            "%vlocity_namespace%__Column__c": "1",
                            "%vlocity_namespace%__EffectiveFromDate__c": "",
                            "%vlocity_namespace%__EffectiveUntilDate__c": "",
                            "%vlocity_namespace%__FieldApiName__c": "ProductCode",
                            "%vlocity_namespace%__GlobalKey__c": "78f506ef-13d4-2d65-30ca-73ceb73e612d",
                            "%vlocity_namespace%__IsActive__c": true,
                            "%vlocity_namespace%__IsRequired__c": true,
                            "%vlocity_namespace%__ObjectSectionId__c": {
                                "Name": "1e859e2b-87de-6bad-e830-e589072bda88",
                                "VlocityDataPackType": "VlocityMatchingKeyObject",
                                "VlocityMatchingRecordSourceKey": "%vlocity_namespace%__ObjectSection__c/1e859e2b-87de-6bad-e830-e589072bda88",
                                "VlocityRecordSObjectType": "%vlocity_namespace%__ObjectSection__c"
                            },
                            "%vlocity_namespace%__Sequence__c": 2,
                            "%vlocity_namespace%__Type__c": "Field",
                            "Name": "Product Code",
                            "VlocityDataPackType": "SObject",
                            "VlocityRecordSObjectType": "%vlocity_namespace%__ObjectElement__c",
                            "VlocityRecordSourceKey": "%vlocity_namespace%__ObjectElement__c/78f506ef-13d4-2d65-30ca-73ceb73e612d"
                        },
                        {
                            "%vlocity_namespace%__AttributeId__c": "",
                            "%vlocity_namespace%__Column__c": "1",
                            "%vlocity_namespace%__EffectiveFromDate__c": "",
                            "%vlocity_namespace%__EffectiveUntilDate__c": "",
                            "%vlocity_namespace%__FieldApiName__c": "Description",
                            "%vlocity_namespace%__GlobalKey__c": "b166a1e2-2f27-e0f1-b6b2-067c9fcd7e8c",
                            "%vlocity_namespace%__IsActive__c": true,
                            "%vlocity_namespace%__IsRequired__c": false,
                            "%vlocity_namespace%__ObjectSectionId__c": {
                                "Name": "1e859e2b-87de-6bad-e830-e589072bda88",
                                "VlocityDataPackType": "VlocityMatchingKeyObject",
                                "VlocityMatchingRecordSourceKey": "%vlocity_namespace%__ObjectSection__c/1e859e2b-87de-6bad-e830-e589072bda88",
                                "VlocityRecordSObjectType": "%vlocity_namespace%__ObjectSection__c"
                            },
                            "%vlocity_namespace%__Sequence__c": 3,
                            "%vlocity_namespace%__Type__c": "Field",
                            "Name": "Description",
                            "VlocityDataPackType": "SObject",
                            "VlocityRecordSObjectType": "%vlocity_namespace%__ObjectElement__c",
                            "VlocityRecordSourceKey": "%vlocity_namespace%__ObjectElement__c/b166a1e2-2f27-e0f1-b6b2-067c9fcd7e8c"
                        },
                        {
                            "%vlocity_namespace%__AttributeId__c": "",
                            "%vlocity_namespace%__Column__c": "1",
                            "%vlocity_namespace%__EffectiveFromDate__c": "",
                            "%vlocity_namespace%__EffectiveUntilDate__c": "",
                            "%vlocity_namespace%__FieldApiName__c": "%vlocity_namespace%__ObjectTypeId__c",
                            "%vlocity_namespace%__GlobalKey__c": "024504b9-31c8-a05e-33ae-bc7e220ecacc",
                            "%vlocity_namespace%__IsActive__c": true,
                            "%vlocity_namespace%__IsRequired__c": false,
                            "%vlocity_namespace%__ObjectSectionId__c": {
                                "Name": "1e859e2b-87de-6bad-e830-e589072bda88",
                                "VlocityDataPackType": "VlocityMatchingKeyObject",
                                "VlocityMatchingRecordSourceKey": "%vlocity_namespace%__ObjectSection__c/1e859e2b-87de-6bad-e830-e589072bda88",
                                "VlocityRecordSObjectType": "%vlocity_namespace%__ObjectSection__c"
                            },
                            "%vlocity_namespace%__Sequence__c": 4,
                            "%vlocity_namespace%__Type__c": "Field",
                            "Name": "Object Type",
                            "VlocityDataPackType": "SObject",
                            "VlocityRecordSObjectType": "%vlocity_namespace%__ObjectElement__c",
                            "VlocityRecordSourceKey": "%vlocity_namespace%__ObjectElement__c/024504b9-31c8-a05e-33ae-bc7e220ecacc"
                        },
                        {
                            "%vlocity_namespace%__AttributeId__c": "",
                            "%vlocity_namespace%__Column__c": "1",
                            "%vlocity_namespace%__EffectiveFromDate__c": "",
                            "%vlocity_namespace%__EffectiveUntilDate__c": "",
                            "%vlocity_namespace%__FieldApiName__c": "%vlocity_namespace%__SpecificationType__c",
                            "%vlocity_namespace%__GlobalKey__c": "b143efe6-9548-a8b0-f1f2-2a1ff0821f5d",
                            "%vlocity_namespace%__IsActive__c": true,
                            "%vlocity_namespace%__IsRequired__c": false,
                            "%vlocity_namespace%__ObjectSectionId__c": {
                                "Name": "1e859e2b-87de-6bad-e830-e589072bda88",
                                "VlocityDataPackType": "VlocityMatchingKeyObject",
                                "VlocityMatchingRecordSourceKey": "%vlocity_namespace%__ObjectSection__c/1e859e2b-87de-6bad-e830-e589072bda88",
                                "VlocityRecordSObjectType": "%vlocity_namespace%__ObjectSection__c"
                            },
                            "%vlocity_namespace%__Sequence__c": 5,
                            "%vlocity_namespace%__Type__c": "Field",
                            "Name": "Specification Type",
                            "VlocityDataPackType": "SObject",
                            "VlocityRecordSObjectType": "%vlocity_namespace%__ObjectElement__c",
                            "VlocityRecordSourceKey": "%vlocity_namespace%__ObjectElement__c/b143efe6-9548-a8b0-f1f2-2a1ff0821f5d"
                        },
                        {
                            "%vlocity_namespace%__AttributeId__c": "",
                            "%vlocity_namespace%__Column__c": "1",
                            "%vlocity_namespace%__EffectiveFromDate__c": "",
                            "%vlocity_namespace%__EffectiveUntilDate__c": "",
                            "%vlocity_namespace%__FieldApiName__c": "%vlocity_namespace%__Status__c",
                            "%vlocity_namespace%__GlobalKey__c": "45979a19-fca5-7527-c2e0-3d6a53307808",
                            "%vlocity_namespace%__IsActive__c": true,
                            "%vlocity_namespace%__IsRequired__c": false,
                            "%vlocity_namespace%__ObjectSectionId__c": {
                                "Name": "1e859e2b-87de-6bad-e830-e589072bda88",
                                "VlocityDataPackType": "VlocityMatchingKeyObject",
                                "VlocityMatchingRecordSourceKey": "%vlocity_namespace%__ObjectSection__c/1e859e2b-87de-6bad-e830-e589072bda88",
                                "VlocityRecordSObjectType": "%vlocity_namespace%__ObjectSection__c"
                            },
                            "%vlocity_namespace%__Sequence__c": 6,
                            "%vlocity_namespace%__Type__c": "Field",
                            "Name": "Status",
                            "VlocityDataPackType": "SObject",
                            "VlocityRecordSObjectType": "%vlocity_namespace%__ObjectElement__c",
                            "VlocityRecordSourceKey": "%vlocity_namespace%__ObjectElement__c/45979a19-fca5-7527-c2e0-3d6a53307808"
                        },
                        {
                            "%vlocity_namespace%__AttributeId__c": "",
                            "%vlocity_namespace%__Column__c": "1",
                            "%vlocity_namespace%__EffectiveFromDate__c": "",
                            "%vlocity_namespace%__EffectiveUntilDate__c": "",
                            "%vlocity_namespace%__FieldApiName__c": "%vlocity_namespace%__IsOrderable__c",
                            "%vlocity_namespace%__GlobalKey__c": "bc30107e-5ffd-1769-69cf-32d8eb863393",
                            "%vlocity_namespace%__IsActive__c": true,
                            "%vlocity_namespace%__IsRequired__c": false,
                            "%vlocity_namespace%__ObjectSectionId__c": {
                                "Name": "1e859e2b-87de-6bad-e830-e589072bda88",
                                "VlocityDataPackType": "VlocityMatchingKeyObject",
                                "VlocityMatchingRecordSourceKey": "%vlocity_namespace%__ObjectSection__c/1e859e2b-87de-6bad-e830-e589072bda88",
                                "VlocityRecordSObjectType": "%vlocity_namespace%__ObjectSection__c"
                            },
                            "%vlocity_namespace%__Sequence__c": 7,
                            "%vlocity_namespace%__Type__c": "Field",
                            "Name": "Orderable",
                            "VlocityDataPackType": "SObject",
                            "VlocityRecordSObjectType": "%vlocity_namespace%__ObjectElement__c",
                            "VlocityRecordSourceKey": "%vlocity_namespace%__ObjectElement__c/bc30107e-5ffd-1769-69cf-32d8eb863393"
                        },
                        {
                            "%vlocity_namespace%__AttributeId__c": "",
                            "%vlocity_namespace%__Column__c": "1",
                            "%vlocity_namespace%__EffectiveFromDate__c": "",
                            "%vlocity_namespace%__EffectiveUntilDate__c": "",
                            "%vlocity_namespace%__FieldApiName__c": "%vlocity_namespace%__Type__c",
                            "%vlocity_namespace%__GlobalKey__c": "4679f95e-3729-31c6-9f6b-d060749be301",
                            "%vlocity_namespace%__IsActive__c": true,
                            "%vlocity_namespace%__IsRequired__c": false,
                            "%vlocity_namespace%__ObjectSectionId__c": {
                                "Name": "1e859e2b-87de-6bad-e830-e589072bda88",
                                "VlocityDataPackType": "VlocityMatchingKeyObject",
                                "VlocityMatchingRecordSourceKey": "%vlocity_namespace%__ObjectSection__c/1e859e2b-87de-6bad-e830-e589072bda88",
                                "VlocityRecordSObjectType": "%vlocity_namespace%__ObjectSection__c"
                            },
                            "%vlocity_namespace%__Sequence__c": 100,
                            "%vlocity_namespace%__Type__c": "Field",
                            "Name": "Type",
                            "VlocityDataPackType": "SObject",
                            "VlocityRecordSObjectType": "%vlocity_namespace%__ObjectElement__c",
                            "VlocityRecordSourceKey": "%vlocity_namespace%__ObjectElement__c/4679f95e-3729-31c6-9f6b-d060749be301"
                        },
                        {
                            "%vlocity_namespace%__AttributeId__c": "",
                            "%vlocity_namespace%__Column__c": "1",
                            "%vlocity_namespace%__EffectiveFromDate__c": "",
                            "%vlocity_namespace%__EffectiveUntilDate__c": "",
                            "%vlocity_namespace%__FieldApiName__c": "%vlocity_namespace%__SubType__c",
                            "%vlocity_namespace%__GlobalKey__c": "bfadb939-1b0f-f069-190d-b71aa003e60a",
                            "%vlocity_namespace%__IsActive__c": true,
                            "%vlocity_namespace%__IsRequired__c": false,
                            "%vlocity_namespace%__ObjectSectionId__c": {
                                "Name": "1e859e2b-87de-6bad-e830-e589072bda88",
                                "VlocityDataPackType": "VlocityMatchingKeyObject",
                                "VlocityMatchingRecordSourceKey": "%vlocity_namespace%__ObjectSection__c/1e859e2b-87de-6bad-e830-e589072bda88",
                                "VlocityRecordSObjectType": "%vlocity_namespace%__ObjectSection__c"
                            },
                            "%vlocity_namespace%__Sequence__c": 110,
                            "%vlocity_namespace%__Type__c": "Field",
                            "Name": "Sub Type",
                            "VlocityDataPackType": "SObject",
                            "VlocityRecordSObjectType": "%vlocity_namespace%__ObjectElement__c",
                            "VlocityRecordSourceKey": "%vlocity_namespace%__ObjectElement__c/bfadb939-1b0f-f069-190d-b71aa003e60a"
                        },
                        {
                            "%vlocity_namespace%__AttributeId__c": "",
                            "%vlocity_namespace%__Column__c": "1",
                            "%vlocity_namespace%__EffectiveFromDate__c": "",
                            "%vlocity_namespace%__EffectiveUntilDate__c": "",
                            "%vlocity_namespace%__FieldApiName__c": "IsActive",
                            "%vlocity_namespace%__GlobalKey__c": "9f35c3f8-dfde-9218-8bf7-7c3ecb250109",
                            "%vlocity_namespace%__IsActive__c": true,
                            "%vlocity_namespace%__IsRequired__c": false,
                            "%vlocity_namespace%__ObjectSectionId__c": {
                                "Name": "1e859e2b-87de-6bad-e830-e589072bda88",
                                "VlocityDataPackType": "VlocityMatchingKeyObject",
                                "VlocityMatchingRecordSourceKey": "%vlocity_namespace%__ObjectSection__c/1e859e2b-87de-6bad-e830-e589072bda88",
                                "VlocityRecordSObjectType": "%vlocity_namespace%__ObjectSection__c"
                            },
                            "%vlocity_namespace%__Sequence__c": "",
                            "%vlocity_namespace%__Type__c": "Field",
                            "Name": "Active",
                            "VlocityDataPackType": "SObject",
                            "VlocityRecordSObjectType": "%vlocity_namespace%__ObjectElement__c",
                            "VlocityRecordSourceKey": "%vlocity_namespace%__ObjectElement__c/9f35c3f8-dfde-9218-8bf7-7c3ecb250109"
                        }
                    ],
                    "%vlocity_namespace%__ObjectFacetId__c": {
                        "Name": "855200d0-0f02-bfb2-e5a4-262408d41124",
                        "VlocityDataPackType": "VlocityMatchingKeyObject",
                        "VlocityMatchingRecordSourceKey": "%vlocity_namespace%__ObjectFacet__c/855200d0-0f02-bfb2-e5a4-262408d41124",
                        "VlocityRecordSObjectType": "%vlocity_namespace%__ObjectFacet__c"
                    },
                    "%vlocity_namespace%__SectionId__c": {
                        "%vlocity_namespace%__GlobalKey__c": "5ceff4783b0f59f31b27417a7064a12c",
                        "VlocityDataPackType": "VlocityLookupMatchingKeyObject",
                        "VlocityLookupRecordSourceKey": "%vlocity_namespace%__UISection__c/5ceff4783b0f59f31b27417a7064a12c",
                        "VlocityRecordSObjectType": "%vlocity_namespace%__UISection__c"
                    },
                    "%vlocity_namespace%__Sequence__c": 1,
                    "%vlocity_namespace%__TabKeyOrder__c": "",
                    "%vlocity_namespace%__ViewType__c": "Field Layout",
                    "%vlocity_namespace%__ViewUri__c": "",
                    "Name": "1e859e2b-87de-6bad-e830-e589072bda88",
                    "VlocityDataPackType": "SObject",
                    "VlocityRecordSObjectType": "%vlocity_namespace%__ObjectSection__c",
                    "VlocityRecordSourceKey": "%vlocity_namespace%__ObjectSection__c/1e859e2b-87de-6bad-e830-e589072bda88"
                },
                {
                    "%vlocity_namespace%__ColumnLayout__c": "",
                    "%vlocity_namespace%__EffectiveFromDate__c": "",
                    "%vlocity_namespace%__EffectiveUntilDate__c": "",
                    "%vlocity_namespace%__GlobalKey__c": "c95d8382-a88b-ad92-e518-38e4e0acf8d2",
                    "%vlocity_namespace%__IsActive__c": true,
                    "%vlocity_namespace%__ObjectElement__c": [
                        {
                            "%vlocity_namespace%__AttributeId__c": "",
                            "%vlocity_namespace%__Column__c": "1",
                            "%vlocity_namespace%__EffectiveFromDate__c": "",
                            "%vlocity_namespace%__EffectiveUntilDate__c": "",
                            "%vlocity_namespace%__FieldApiName__c": "IsActive",
                            "%vlocity_namespace%__GlobalKey__c": "ad0c9be2-fb5d-3f39-e190-9f595cf02958",
                            "%vlocity_namespace%__IsActive__c": true,
                            "%vlocity_namespace%__IsRequired__c": false,
                            "%vlocity_namespace%__ObjectSectionId__c": {
                                "Name": "c95d8382-a88b-ad92-e518-38e4e0acf8d2",
                                "VlocityDataPackType": "VlocityMatchingKeyObject",
                                "VlocityMatchingRecordSourceKey": "%vlocity_namespace%__ObjectSection__c/c95d8382-a88b-ad92-e518-38e4e0acf8d2",
                                "VlocityRecordSObjectType": "%vlocity_namespace%__ObjectSection__c"
                            },
                            "%vlocity_namespace%__Sequence__c": 1,
                            "%vlocity_namespace%__Type__c": "Field",
                            "Name": "Active",
                            "VlocityDataPackType": "SObject",
                            "VlocityRecordSObjectType": "%vlocity_namespace%__ObjectElement__c",
                            "VlocityRecordSourceKey": "%vlocity_namespace%__ObjectElement__c/ad0c9be2-fb5d-3f39-e190-9f595cf02958"
                        },
                        {
                            "%vlocity_namespace%__AttributeId__c": "",
                            "%vlocity_namespace%__Column__c": "1",
                            "%vlocity_namespace%__EffectiveFromDate__c": "",
                            "%vlocity_namespace%__EffectiveUntilDate__c": "",
                            "%vlocity_namespace%__FieldApiName__c": "%vlocity_namespace%__EffectiveDate__c",
                            "%vlocity_namespace%__GlobalKey__c": "1eeef15a-0383-e24d-b166-d25c9b1b7729",
                            "%vlocity_namespace%__IsActive__c": true,
                            "%vlocity_namespace%__IsRequired__c": false,
                            "%vlocity_namespace%__ObjectSectionId__c": {
                                "Name": "c95d8382-a88b-ad92-e518-38e4e0acf8d2",
                                "VlocityDataPackType": "VlocityMatchingKeyObject",
                                "VlocityMatchingRecordSourceKey": "%vlocity_namespace%__ObjectSection__c/c95d8382-a88b-ad92-e518-38e4e0acf8d2",
                                "VlocityRecordSObjectType": "%vlocity_namespace%__ObjectSection__c"
                            },
                            "%vlocity_namespace%__Sequence__c": 2,
                            "%vlocity_namespace%__Type__c": "Field",
                            "Name": "Effective Start Date",
                            "VlocityDataPackType": "SObject",
                            "VlocityRecordSObjectType": "%vlocity_namespace%__ObjectElement__c",
                            "VlocityRecordSourceKey": "%vlocity_namespace%__ObjectElement__c/1eeef15a-0383-e24d-b166-d25c9b1b7729"
                        },
                        {
                            "%vlocity_namespace%__AttributeId__c": "",
                            "%vlocity_namespace%__Column__c": "1",
                            "%vlocity_namespace%__EffectiveFromDate__c": "",
                            "%vlocity_namespace%__EffectiveUntilDate__c": "",
                            "%vlocity_namespace%__FieldApiName__c": "%vlocity_namespace%__EndDate__c",
                            "%vlocity_namespace%__GlobalKey__c": "6a1f3a94-4cb7-b8ea-a998-3a616f86342f",
                            "%vlocity_namespace%__IsActive__c": true,
                            "%vlocity_namespace%__IsRequired__c": false,
                            "%vlocity_namespace%__ObjectSectionId__c": {
                                "Name": "c95d8382-a88b-ad92-e518-38e4e0acf8d2",
                                "VlocityDataPackType": "VlocityMatchingKeyObject",
                                "VlocityMatchingRecordSourceKey": "%vlocity_namespace%__ObjectSection__c/c95d8382-a88b-ad92-e518-38e4e0acf8d2",
                                "VlocityRecordSObjectType": "%vlocity_namespace%__ObjectSection__c"
                            },
                            "%vlocity_namespace%__Sequence__c": 3,
                            "%vlocity_namespace%__Type__c": "Field",
                            "Name": "Effective End Date",
                            "VlocityDataPackType": "SObject",
                            "VlocityRecordSObjectType": "%vlocity_namespace%__ObjectElement__c",
                            "VlocityRecordSourceKey": "%vlocity_namespace%__ObjectElement__c/6a1f3a94-4cb7-b8ea-a998-3a616f86342f"
                        }
                    ],
                    "%vlocity_namespace%__ObjectFacetId__c": {
                        "Name": "855200d0-0f02-bfb2-e5a4-262408d41124",
                        "VlocityDataPackType": "VlocityMatchingKeyObject",
                        "VlocityMatchingRecordSourceKey": "%vlocity_namespace%__ObjectFacet__c/855200d0-0f02-bfb2-e5a4-262408d41124",
                        "VlocityRecordSObjectType": "%vlocity_namespace%__ObjectFacet__c"
                    },
                    "%vlocity_namespace%__SectionId__c": {
                        "%vlocity_namespace%__GlobalKey__c": "07fb6c10c8822dcf5708e0b13836de9d",
                        "VlocityDataPackType": "VlocityLookupMatchingKeyObject",
                        "VlocityLookupRecordSourceKey": "%vlocity_namespace%__UISection__c/07fb6c10c8822dcf5708e0b13836de9d",
                        "VlocityRecordSObjectType": "%vlocity_namespace%__UISection__c"
                    },
                    "%vlocity_namespace%__Sequence__c": 2,
                    "%vlocity_namespace%__TabKeyOrder__c": "",
                    "%vlocity_namespace%__ViewType__c": "Field Layout",
                    "%vlocity_namespace%__ViewUri__c": "",
                    "Name": "c95d8382-a88b-ad92-e518-38e4e0acf8d2",
                    "VlocityDataPackType": "SObject",
                    "VlocityRecordSObjectType": "%vlocity_namespace%__ObjectSection__c",
                    "VlocityRecordSourceKey": "%vlocity_namespace%__ObjectSection__c/c95d8382-a88b-ad92-e518-38e4e0acf8d2"
                },
                {
                    "%vlocity_namespace%__ColumnLayout__c": "",
                    "%vlocity_namespace%__EffectiveFromDate__c": "",
                    "%vlocity_namespace%__EffectiveUntilDate__c": "",
                    "%vlocity_namespace%__GlobalKey__c": "064145ee-35e6-84eb-1a6c-5b69a6dffc35",
                    "%vlocity_namespace%__IsActive__c": true,
                    "%vlocity_namespace%__ObjectElement__c": [
                        {
                            "%vlocity_namespace%__AttributeCategoryId__c": {
                                "%vlocity_namespace%__Code__c": "VLO-PRO-0024",
                                "VlocityDataPackType": "VlocityLookupMatchingKeyObject",
                                "VlocityLookupRecordSourceKey": "%vlocity_namespace%__AttributeCategory__c/VLO-PRO-0024",
                                "VlocityRecordSObjectType": "%vlocity_namespace%__AttributeCategory__c"
                            },
                            "%vlocity_namespace%__AttributeId__c": {
                                "%vlocity_namespace%__Code__c": "ATT-ATTR-BW-003",
                                "VlocityDataPackType": "VlocityLookupMatchingKeyObject",
                                "VlocityLookupRecordSourceKey": "%vlocity_namespace%__Attribute__c/ATT-ATTR-BW-003",
                                "VlocityRecordSObjectType": "%vlocity_namespace%__Attribute__c"
                            },
                            "%vlocity_namespace%__Column__c": "1",
                            "%vlocity_namespace%__EffectiveFromDate__c": "",
                            "%vlocity_namespace%__EffectiveUntilDate__c": "",
                            "%vlocity_namespace%__FieldApiName__c": "",
                            "%vlocity_namespace%__GlobalKey__c": "43c4bea3-8cd6-c39c-d51c-c8e29865944e",
                            "%vlocity_namespace%__IsActive__c": true,
                            "%vlocity_namespace%__IsRequired__c": false,
                            "%vlocity_namespace%__ObjectSectionId__c": {
                                "Name": "064145ee-35e6-84eb-1a6c-5b69a6dffc35",
                                "VlocityDataPackType": "VlocityMatchingKeyObject",
                                "VlocityMatchingRecordSourceKey": "%vlocity_namespace%__ObjectSection__c/064145ee-35e6-84eb-1a6c-5b69a6dffc35",
                                "VlocityRecordSObjectType": "%vlocity_namespace%__ObjectSection__c"
                            },
                            "%vlocity_namespace%__Sequence__c": 10,
                            "%vlocity_namespace%__Type__c": "Attribute",
                            "Name": "Committed Bandwidth",
                            "VlocityDataPackType": "SObject",
                            "VlocityRecordSObjectType": "%vlocity_namespace%__ObjectElement__c",
                            "VlocityRecordSourceKey": "%vlocity_namespace%__ObjectElement__c/43c4bea3-8cd6-c39c-d51c-c8e29865944e"
                        },
                        {
                            "%vlocity_namespace%__AttributeCategoryId__c": {
                                "%vlocity_namespace%__Code__c": "VLO-PRO-0024",
                                "VlocityDataPackType": "VlocityLookupMatchingKeyObject",
                                "VlocityLookupRecordSourceKey": "%vlocity_namespace%__AttributeCategory__c/VLO-PRO-0024",
                                "VlocityRecordSObjectType": "%vlocity_namespace%__AttributeCategory__c"
                            },
                            "%vlocity_namespace%__AttributeId__c": {
                                "%vlocity_namespace%__Code__c": "ATTR-PLAN-001",
                                "VlocityDataPackType": "VlocityLookupMatchingKeyObject",
                                "VlocityLookupRecordSourceKey": "%vlocity_namespace%__Attribute__c/ATTR-PLAN-001",
                                "VlocityRecordSObjectType": "%vlocity_namespace%__Attribute__c"
                            },
                            "%vlocity_namespace%__Column__c": "1",
                            "%vlocity_namespace%__EffectiveFromDate__c": "",
                            "%vlocity_namespace%__EffectiveUntilDate__c": "",
                            "%vlocity_namespace%__FieldApiName__c": "",
                            "%vlocity_namespace%__GlobalKey__c": "7f979690-e1d1-0aaf-04ea-e99964279058",
                            "%vlocity_namespace%__IsActive__c": true,
                            "%vlocity_namespace%__IsRequired__c": false,
                            "%vlocity_namespace%__ObjectSectionId__c": {
                                "Name": "064145ee-35e6-84eb-1a6c-5b69a6dffc35",
                                "VlocityDataPackType": "VlocityMatchingKeyObject",
                                "VlocityMatchingRecordSourceKey": "%vlocity_namespace%__ObjectSection__c/064145ee-35e6-84eb-1a6c-5b69a6dffc35",
                                "VlocityRecordSObjectType": "%vlocity_namespace%__ObjectSection__c"
                            },
                            "%vlocity_namespace%__Sequence__c": 20,
                            "%vlocity_namespace%__Type__c": "Attribute",
                            "Name": "Usage Type",
                            "VlocityDataPackType": "SObject",
                            "VlocityRecordSObjectType": "%vlocity_namespace%__ObjectElement__c",
                            "VlocityRecordSourceKey": "%vlocity_namespace%__ObjectElement__c/7f979690-e1d1-0aaf-04ea-e99964279058"
                        },
                        {
                            "%vlocity_namespace%__AttributeCategoryId__c": {
                                "%vlocity_namespace%__Code__c": "VLO-PRO-0006",
                                "VlocityDataPackType": "VlocityLookupMatchingKeyObject",
                                "VlocityLookupRecordSourceKey": "%vlocity_namespace%__AttributeCategory__c/VLO-PRO-0006",
                                "VlocityRecordSObjectType": "%vlocity_namespace%__AttributeCategory__c"
                            },
                            "%vlocity_namespace%__AttributeId__c": {
                                "%vlocity_namespace%__Code__c": "ATTRIBUTE-153",
                                "VlocityDataPackType": "VlocityLookupMatchingKeyObject",
                                "VlocityLookupRecordSourceKey": "%vlocity_namespace%__Attribute__c/ATTRIBUTE-153",
                                "VlocityRecordSObjectType": "%vlocity_namespace%__Attribute__c"
                            },
                            "%vlocity_namespace%__Column__c": "1",
                            "%vlocity_namespace%__EffectiveFromDate__c": "",
                            "%vlocity_namespace%__EffectiveUntilDate__c": "",
                            "%vlocity_namespace%__FieldApiName__c": "",
                            "%vlocity_namespace%__GlobalKey__c": "6fb37f9a-b01d-046f-67d4-eadde3cfd49b",
                            "%vlocity_namespace%__IsActive__c": true,
                            "%vlocity_namespace%__IsRequired__c": false,
                            "%vlocity_namespace%__ObjectSectionId__c": {
                                "Name": "064145ee-35e6-84eb-1a6c-5b69a6dffc35",
                                "VlocityDataPackType": "VlocityMatchingKeyObject",
                                "VlocityMatchingRecordSourceKey": "%vlocity_namespace%__ObjectSection__c/064145ee-35e6-84eb-1a6c-5b69a6dffc35",
                                "VlocityRecordSObjectType": "%vlocity_namespace%__ObjectSection__c"
                            },
                            "%vlocity_namespace%__Sequence__c": 30,
                            "%vlocity_namespace%__Type__c": "Attribute",
                            "Name": "Access Speed",
                            "VlocityDataPackType": "SObject",
                            "VlocityRecordSObjectType": "%vlocity_namespace%__ObjectElement__c",
                            "VlocityRecordSourceKey": "%vlocity_namespace%__ObjectElement__c/6fb37f9a-b01d-046f-67d4-eadde3cfd49b"
                        },
                        {
                            "%vlocity_namespace%__AttributeCategoryId__c": {
                                "%vlocity_namespace%__Code__c": "VLO-PRO-0006",
                                "VlocityDataPackType": "VlocityLookupMatchingKeyObject",
                                "VlocityLookupRecordSourceKey": "%vlocity_namespace%__AttributeCategory__c/VLO-PRO-0006",
                                "VlocityRecordSObjectType": "%vlocity_namespace%__AttributeCategory__c"
                            },
                            "%vlocity_namespace%__AttributeId__c": {
                                "%vlocity_namespace%__Code__c": "ATTRIBUTE-152",
                                "VlocityDataPackType": "VlocityLookupMatchingKeyObject",
                                "VlocityLookupRecordSourceKey": "%vlocity_namespace%__Attribute__c/ATTRIBUTE-152",
                                "VlocityRecordSObjectType": "%vlocity_namespace%__Attribute__c"
                            },
                            "%vlocity_namespace%__Column__c": "1",
                            "%vlocity_namespace%__EffectiveFromDate__c": "",
                            "%vlocity_namespace%__EffectiveUntilDate__c": "",
                            "%vlocity_namespace%__FieldApiName__c": "",
                            "%vlocity_namespace%__GlobalKey__c": "b651f4b7-ba4f-f6ce-be30-f7deb75f3d88",
                            "%vlocity_namespace%__IsActive__c": true,
                            "%vlocity_namespace%__IsRequired__c": false,
                            "%vlocity_namespace%__ObjectSectionId__c": {
                                "Name": "064145ee-35e6-84eb-1a6c-5b69a6dffc35",
                                "VlocityDataPackType": "VlocityMatchingKeyObject",
                                "VlocityMatchingRecordSourceKey": "%vlocity_namespace%__ObjectSection__c/064145ee-35e6-84eb-1a6c-5b69a6dffc35",
                                "VlocityRecordSObjectType": "%vlocity_namespace%__ObjectSection__c"
                            },
                            "%vlocity_namespace%__Sequence__c": 40,
                            "%vlocity_namespace%__Type__c": "Attribute",
                            "Name": "Access Type",
                            "VlocityDataPackType": "SObject",
                            "VlocityRecordSObjectType": "%vlocity_namespace%__ObjectElement__c",
                            "VlocityRecordSourceKey": "%vlocity_namespace%__ObjectElement__c/b651f4b7-ba4f-f6ce-be30-f7deb75f3d88"
                        },
                        {
                            "%vlocity_namespace%__AttributeCategoryId__c": {
                                "%vlocity_namespace%__Code__c": "VLO-PRO-0025",
                                "VlocityDataPackType": "VlocityLookupMatchingKeyObject",
                                "VlocityLookupRecordSourceKey": "%vlocity_namespace%__AttributeCategory__c/VLO-PRO-0025",
                                "VlocityRecordSObjectType": "%vlocity_namespace%__AttributeCategory__c"
                            },
                            "%vlocity_namespace%__AttributeId__c": {
                                "%vlocity_namespace%__Code__c": "B2B-ATTR-CUSTOMER-CPE-ROUTER",
                                "VlocityDataPackType": "VlocityLookupMatchingKeyObject",
                                "VlocityLookupRecordSourceKey": "%vlocity_namespace%__Attribute__c/B2B-ATTR-CUSTOMER-CPE-ROUTER",
                                "VlocityRecordSObjectType": "%vlocity_namespace%__Attribute__c"
                            },
                            "%vlocity_namespace%__Column__c": "1",
                            "%vlocity_namespace%__EffectiveFromDate__c": "",
                            "%vlocity_namespace%__EffectiveUntilDate__c": "",
                            "%vlocity_namespace%__FieldApiName__c": "",
                            "%vlocity_namespace%__GlobalKey__c": "22693f3d-1c42-7840-b85d-54052f247d35",
                            "%vlocity_namespace%__IsActive__c": true,
                            "%vlocity_namespace%__IsRequired__c": false,
                            "%vlocity_namespace%__ObjectSectionId__c": {
                                "Name": "064145ee-35e6-84eb-1a6c-5b69a6dffc35",
                                "VlocityDataPackType": "VlocityMatchingKeyObject",
                                "VlocityMatchingRecordSourceKey": "%vlocity_namespace%__ObjectSection__c/064145ee-35e6-84eb-1a6c-5b69a6dffc35",
                                "VlocityRecordSObjectType": "%vlocity_namespace%__ObjectSection__c"
                            },
                            "%vlocity_namespace%__Sequence__c": 50,
                            "%vlocity_namespace%__Type__c": "Attribute",
                            "Name": "Customer Owned CPE Router",
                            "VlocityDataPackType": "SObject",
                            "VlocityRecordSObjectType": "%vlocity_namespace%__ObjectElement__c",
                            "VlocityRecordSourceKey": "%vlocity_namespace%__ObjectElement__c/22693f3d-1c42-7840-b85d-54052f247d35"
                        }
                    ],
                    "%vlocity_namespace%__ObjectFacetId__c": {
                        "Name": "855200d0-0f02-bfb2-e5a4-262408d41124",
                        "VlocityDataPackType": "VlocityMatchingKeyObject",
                        "VlocityMatchingRecordSourceKey": "%vlocity_namespace%__ObjectFacet__c/855200d0-0f02-bfb2-e5a4-262408d41124",
                        "VlocityRecordSObjectType": "%vlocity_namespace%__ObjectFacet__c"
                    },
                    "%vlocity_namespace%__SectionId__c": {
                        "%vlocity_namespace%__GlobalKey__c": "5c689311099006eead7f2a118192bf5a",
                        "VlocityDataPackType": "VlocityLookupMatchingKeyObject",
                        "VlocityLookupRecordSourceKey": "%vlocity_namespace%__UISection__c/5c689311099006eead7f2a118192bf5a",
                        "VlocityRecordSObjectType": "%vlocity_namespace%__UISection__c"
                    },
                    "%vlocity_namespace%__Sequence__c": 3,
                    "%vlocity_namespace%__TabKeyOrder__c": "",
                    "%vlocity_namespace%__ViewType__c": "Field Layout",
                    "%vlocity_namespace%__ViewUri__c": "",
                    "Name": "064145ee-35e6-84eb-1a6c-5b69a6dffc35",
                    "VlocityDataPackType": "SObject",
                    "VlocityRecordSObjectType": "%vlocity_namespace%__ObjectSection__c",
                    "VlocityRecordSourceKey": "%vlocity_namespace%__ObjectSection__c/064145ee-35e6-84eb-1a6c-5b69a6dffc35"
                }
            ],
            "%vlocity_namespace%__Sequence__c": 1,
            "Name": "855200d0-0f02-bfb2-e5a4-262408d41124",
            "VlocityDataPackType": "SObject",
            "VlocityRecordSObjectType": "%vlocity_namespace%__ObjectFacet__c",
            "VlocityRecordSourceKey": "%vlocity_namespace%__ObjectFacet__c/855200d0-0f02-bfb2-e5a4-262408d41124"
        },
        {
            "%vlocity_namespace%__EffectiveFromDate__c": "",
            "%vlocity_namespace%__EffectiveUntilDate__c": "",
            "%vlocity_namespace%__FacetId__c": {
                "%vlocity_namespace%__GlobalKey__c": "885e10262c2299afdcd1aa6e95138717",
                "VlocityDataPackType": "VlocityLookupMatchingKeyObject",
                "VlocityLookupRecordSourceKey": "%vlocity_namespace%__UIFacet__c/885e10262c2299afdcd1aa6e95138717",
                "VlocityRecordSObjectType": "%vlocity_namespace%__UIFacet__c"
            },
            "%vlocity_namespace%__GlobalKey__c": "c26c6aa6-fa07-e42e-ccc2-3357a6c1c2b0",
            "%vlocity_namespace%__IsActive__c": true,
            "%vlocity_namespace%__ObjectLayoutId__c": {
                "%vlocity_namespace%__GlobalKey__c": "d2bca9c3-fcb7-ab6b-fa63-19ec4973776d",
                "VlocityDataPackType": "VlocityMatchingKeyObject",
                "VlocityMatchingRecordSourceKey": "%vlocity_namespace%__ObjectLayout__c/d2bca9c3-fcb7-ab6b-fa63-19ec4973776d",
                "VlocityRecordSObjectType": "%vlocity_namespace%__ObjectLayout__c"
            },
            "%vlocity_namespace%__ObjectSection__c": [
                {
                    "%vlocity_namespace%__ColumnLayout__c": "",
                    "%vlocity_namespace%__EffectiveFromDate__c": "",
                    "%vlocity_namespace%__EffectiveUntilDate__c": "",
                    "%vlocity_namespace%__GlobalKey__c": "668fb8a6-6c25-4321-c9be-0b6a2449ddb5",
                    "%vlocity_namespace%__IsActive__c": true,
                    "%vlocity_namespace%__ObjectFacetId__c": {
                        "Name": "c26c6aa6-fa07-e42e-ccc2-3357a6c1c2b0",
                        "VlocityDataPackType": "VlocityMatchingKeyObject",
                        "VlocityMatchingRecordSourceKey": "%vlocity_namespace%__ObjectFacet__c/c26c6aa6-fa07-e42e-ccc2-3357a6c1c2b0",
                        "VlocityRecordSObjectType": "%vlocity_namespace%__ObjectFacet__c"
                    },
                    "%vlocity_namespace%__SectionId__c": {
                        "%vlocity_namespace%__GlobalKey__c": "885e10262c2299afdcd1aa6e95138717",
                        "VlocityDataPackType": "VlocityLookupMatchingKeyObject",
                        "VlocityLookupRecordSourceKey": "%vlocity_namespace%__UISection__c/885e10262c2299afdcd1aa6e95138717",
                        "VlocityRecordSObjectType": "%vlocity_namespace%__UISection__c"
                    },
                    "%vlocity_namespace%__Sequence__c": 1,
                    "%vlocity_namespace%__TabKeyOrder__c": "",
                    "%vlocity_namespace%__ViewType__c": "Custom View",
                    "%vlocity_namespace%__ViewUri__c": "VlocObjAttrsFields",
                    "Name": "668fb8a6-6c25-4321-c9be-0b6a2449ddb5",
                    "VlocityDataPackType": "SObject",
                    "VlocityRecordSObjectType": "%vlocity_namespace%__ObjectSection__c",
                    "VlocityRecordSourceKey": "%vlocity_namespace%__ObjectSection__c/668fb8a6-6c25-4321-c9be-0b6a2449ddb5"
                }
            ],
            "%vlocity_namespace%__Sequence__c": 2,
            "Name": "c26c6aa6-fa07-e42e-ccc2-3357a6c1c2b0",
            "VlocityDataPackType": "SObject",
            "VlocityRecordSObjectType": "%vlocity_namespace%__ObjectFacet__c",
            "VlocityRecordSourceKey": "%vlocity_namespace%__ObjectFacet__c/c26c6aa6-fa07-e42e-ccc2-3357a6c1c2b0"
        },
        {
            "%vlocity_namespace%__EffectiveFromDate__c": "",
            "%vlocity_namespace%__EffectiveUntilDate__c": "",
            "%vlocity_namespace%__FacetId__c": {
                "%vlocity_namespace%__GlobalKey__c": "7e2708aeb65763c54052f57ed1a1ec1d",
                "VlocityDataPackType": "VlocityLookupMatchingKeyObject",
                "VlocityLookupRecordSourceKey": "%vlocity_namespace%__UIFacet__c/7e2708aeb65763c54052f57ed1a1ec1d",
                "VlocityRecordSObjectType": "%vlocity_namespace%__UIFacet__c"
            },
            "%vlocity_namespace%__GlobalKey__c": "37da7013-c653-e04a-9357-ef7a61d4dc75",
            "%vlocity_namespace%__IsActive__c": true,
            "%vlocity_namespace%__ObjectLayoutId__c": {
                "%vlocity_namespace%__GlobalKey__c": "d2bca9c3-fcb7-ab6b-fa63-19ec4973776d",
                "VlocityDataPackType": "VlocityMatchingKeyObject",
                "VlocityMatchingRecordSourceKey": "%vlocity_namespace%__ObjectLayout__c/d2bca9c3-fcb7-ab6b-fa63-19ec4973776d",
                "VlocityRecordSObjectType": "%vlocity_namespace%__ObjectLayout__c"
            },
            "%vlocity_namespace%__ObjectSection__c": [
                {
                    "%vlocity_namespace%__ColumnLayout__c": "",
                    "%vlocity_namespace%__EffectiveFromDate__c": "",
                    "%vlocity_namespace%__EffectiveUntilDate__c": "",
                    "%vlocity_namespace%__GlobalKey__c": "6b90d23c-dae7-6cb0-074e-a3992fabb1e8",
                    "%vlocity_namespace%__IsActive__c": true,
                    "%vlocity_namespace%__ObjectFacetId__c": {
                        "Name": "37da7013-c653-e04a-9357-ef7a61d4dc75",
                        "VlocityDataPackType": "VlocityMatchingKeyObject",
                        "VlocityMatchingRecordSourceKey": "%vlocity_namespace%__ObjectFacet__c/37da7013-c653-e04a-9357-ef7a61d4dc75",
                        "VlocityRecordSObjectType": "%vlocity_namespace%__ObjectFacet__c"
                    },
                    "%vlocity_namespace%__SectionId__c": {
                        "%vlocity_namespace%__GlobalKey__c": "7e2708aeb65763c54052f57ed1a1ec1d",
                        "VlocityDataPackType": "VlocityLookupMatchingKeyObject",
                        "VlocityLookupRecordSourceKey": "%vlocity_namespace%__UISection__c/7e2708aeb65763c54052f57ed1a1ec1d",
                        "VlocityRecordSObjectType": "%vlocity_namespace%__UISection__c"
                    },
                    "%vlocity_namespace%__Sequence__c": 1,
                    "%vlocity_namespace%__TabKeyOrder__c": "",
                    "%vlocity_namespace%__ViewType__c": "Custom View",
                    "%vlocity_namespace%__ViewUri__c": "Attachments",
                    "Name": "6b90d23c-dae7-6cb0-074e-a3992fabb1e8",
                    "VlocityDataPackType": "SObject",
                    "VlocityRecordSObjectType": "%vlocity_namespace%__ObjectSection__c",
                    "VlocityRecordSourceKey": "%vlocity_namespace%__ObjectSection__c/6b90d23c-dae7-6cb0-074e-a3992fabb1e8"
                }
            ],
            "%vlocity_namespace%__Sequence__c": 3,
            "Name": "37da7013-c653-e04a-9357-ef7a61d4dc75",
            "VlocityDataPackType": "SObject",
            "VlocityRecordSObjectType": "%vlocity_namespace%__ObjectFacet__c",
            "VlocityRecordSourceKey": "%vlocity_namespace%__ObjectFacet__c/37da7013-c653-e04a-9357-ef7a61d4dc75"
        },
        {
            "%vlocity_namespace%__EffectiveFromDate__c": "",
            "%vlocity_namespace%__EffectiveUntilDate__c": "",
            "%vlocity_namespace%__FacetId__c": {
                "%vlocity_namespace%__GlobalKey__c": "88133f31931c2d3463baa8f14230978f",
                "VlocityDataPackType": "VlocityLookupMatchingKeyObject",
                "VlocityLookupRecordSourceKey": "%vlocity_namespace%__UIFacet__c/88133f31931c2d3463baa8f14230978f",
                "VlocityRecordSObjectType": "%vlocity_namespace%__UIFacet__c"
            },
            "%vlocity_namespace%__GlobalKey__c": "d8a369d7-829e-bab4-b7f1-bb94691b8590",
            "%vlocity_namespace%__IsActive__c": true,
            "%vlocity_namespace%__ObjectLayoutId__c": {
                "%vlocity_namespace%__GlobalKey__c": "d2bca9c3-fcb7-ab6b-fa63-19ec4973776d",
                "VlocityDataPackType": "VlocityMatchingKeyObject",
                "VlocityMatchingRecordSourceKey": "%vlocity_namespace%__ObjectLayout__c/d2bca9c3-fcb7-ab6b-fa63-19ec4973776d",
                "VlocityRecordSObjectType": "%vlocity_namespace%__ObjectLayout__c"
            },
            "%vlocity_namespace%__ObjectSection__c": [
                {
                    "%vlocity_namespace%__ColumnLayout__c": "",
                    "%vlocity_namespace%__EffectiveFromDate__c": "",
                    "%vlocity_namespace%__EffectiveUntilDate__c": "",
                    "%vlocity_namespace%__GlobalKey__c": "8cbc107a-4e57-459e-217a-091b145d1497",
                    "%vlocity_namespace%__IsActive__c": true,
                    "%vlocity_namespace%__ObjectFacetId__c": {
                        "Name": "d8a369d7-829e-bab4-b7f1-bb94691b8590",
                        "VlocityDataPackType": "VlocityMatchingKeyObject",
                        "VlocityMatchingRecordSourceKey": "%vlocity_namespace%__ObjectFacet__c/d8a369d7-829e-bab4-b7f1-bb94691b8590",
                        "VlocityRecordSObjectType": "%vlocity_namespace%__ObjectFacet__c"
                    },
                    "%vlocity_namespace%__SectionId__c": {
                        "%vlocity_namespace%__GlobalKey__c": "88133f31931c2d3463baa8f14230978f",
                        "VlocityDataPackType": "VlocityLookupMatchingKeyObject",
                        "VlocityLookupRecordSourceKey": "%vlocity_namespace%__UISection__c/88133f31931c2d3463baa8f14230978f",
                        "VlocityRecordSObjectType": "%vlocity_namespace%__UISection__c"
                    },
                    "%vlocity_namespace%__Sequence__c": 1,
                    "%vlocity_namespace%__TabKeyOrder__c": "",
                    "%vlocity_namespace%__ViewType__c": "Custom View",
                    "%vlocity_namespace%__ViewUri__c": "ProductStructure",
                    "Name": "8cbc107a-4e57-459e-217a-091b145d1497",
                    "VlocityDataPackType": "SObject",
                    "VlocityRecordSObjectType": "%vlocity_namespace%__ObjectSection__c",
                    "VlocityRecordSourceKey": "%vlocity_namespace%__ObjectSection__c/8cbc107a-4e57-459e-217a-091b145d1497"
                }
            ],
            "%vlocity_namespace%__Sequence__c": 4,
            "Name": "d8a369d7-829e-bab4-b7f1-bb94691b8590",
            "VlocityDataPackType": "SObject",
            "VlocityRecordSObjectType": "%vlocity_namespace%__ObjectFacet__c",
            "VlocityRecordSourceKey": "%vlocity_namespace%__ObjectFacet__c/d8a369d7-829e-bab4-b7f1-bb94691b8590"
        },
        {
            "%vlocity_namespace%__EffectiveFromDate__c": "",
            "%vlocity_namespace%__EffectiveUntilDate__c": "",
            "%vlocity_namespace%__FacetId__c": {
                "%vlocity_namespace%__GlobalKey__c": "e22ac25b066b201473de7aa700ef5d92",
                "VlocityDataPackType": "VlocityLookupMatchingKeyObject",
                "VlocityLookupRecordSourceKey": "%vlocity_namespace%__UIFacet__c/e22ac25b066b201473de7aa700ef5d92",
                "VlocityRecordSObjectType": "%vlocity_namespace%__UIFacet__c"
            },
            "%vlocity_namespace%__GlobalKey__c": "079d08f1-3d74-db01-4d49-e1699eaba716",
            "%vlocity_namespace%__IsActive__c": true,
            "%vlocity_namespace%__ObjectLayoutId__c": {
                "%vlocity_namespace%__GlobalKey__c": "d2bca9c3-fcb7-ab6b-fa63-19ec4973776d",
                "VlocityDataPackType": "VlocityMatchingKeyObject",
                "VlocityMatchingRecordSourceKey": "%vlocity_namespace%__ObjectLayout__c/d2bca9c3-fcb7-ab6b-fa63-19ec4973776d",
                "VlocityRecordSObjectType": "%vlocity_namespace%__ObjectLayout__c"
            },
            "%vlocity_namespace%__ObjectSection__c": [
                {
                    "%vlocity_namespace%__ColumnLayout__c": "",
                    "%vlocity_namespace%__EffectiveFromDate__c": "",
                    "%vlocity_namespace%__EffectiveUntilDate__c": "",
                    "%vlocity_namespace%__GlobalKey__c": "f0bf68c8-582a-9380-2896-2b71233f51eb",
                    "%vlocity_namespace%__IsActive__c": true,
                    "%vlocity_namespace%__ObjectFacetId__c": {
                        "Name": "079d08f1-3d74-db01-4d49-e1699eaba716",
                        "VlocityDataPackType": "VlocityMatchingKeyObject",
                        "VlocityMatchingRecordSourceKey": "%vlocity_namespace%__ObjectFacet__c/079d08f1-3d74-db01-4d49-e1699eaba716",
                        "VlocityRecordSObjectType": "%vlocity_namespace%__ObjectFacet__c"
                    },
                    "%vlocity_namespace%__SectionId__c": {
                        "%vlocity_namespace%__GlobalKey__c": "e22ac25b066b201473de7aa700ef5d92",
                        "VlocityDataPackType": "VlocityLookupMatchingKeyObject",
                        "VlocityLookupRecordSourceKey": "%vlocity_namespace%__UISection__c/e22ac25b066b201473de7aa700ef5d92",
                        "VlocityRecordSObjectType": "%vlocity_namespace%__UISection__c"
                    },
                    "%vlocity_namespace%__Sequence__c": 1,
                    "%vlocity_namespace%__TabKeyOrder__c": "",
                    "%vlocity_namespace%__ViewType__c": "Custom View",
                    "%vlocity_namespace%__ViewUri__c": "ObjectPricing",
                    "Name": "f0bf68c8-582a-9380-2896-2b71233f51eb",
                    "VlocityDataPackType": "SObject",
                    "VlocityRecordSObjectType": "%vlocity_namespace%__ObjectSection__c",
                    "VlocityRecordSourceKey": "%vlocity_namespace%__ObjectSection__c/f0bf68c8-582a-9380-2896-2b71233f51eb"
                }
            ],
            "%vlocity_namespace%__Sequence__c": 5,
            "Name": "079d08f1-3d74-db01-4d49-e1699eaba716",
            "VlocityDataPackType": "SObject",
            "VlocityRecordSObjectType": "%vlocity_namespace%__ObjectFacet__c",
            "VlocityRecordSourceKey": "%vlocity_namespace%__ObjectFacet__c/079d08f1-3d74-db01-4d49-e1699eaba716"
        },
        {
            "%vlocity_namespace%__EffectiveFromDate__c": "",
            "%vlocity_namespace%__EffectiveUntilDate__c": "",
            "%vlocity_namespace%__FacetId__c": {
                "%vlocity_namespace%__GlobalKey__c": "f3ace7a9322ba258081738b2a79fb02a",
                "VlocityDataPackType": "VlocityLookupMatchingKeyObject",
                "VlocityLookupRecordSourceKey": "%vlocity_namespace%__UIFacet__c/f3ace7a9322ba258081738b2a79fb02a",
                "VlocityRecordSObjectType": "%vlocity_namespace%__UIFacet__c"
            },
            "%vlocity_namespace%__GlobalKey__c": "6db5c80f-7285-5bcd-4013-6d6a9aa9d64a",
            "%vlocity_namespace%__IsActive__c": true,
            "%vlocity_namespace%__ObjectLayoutId__c": {
                "%vlocity_namespace%__GlobalKey__c": "d2bca9c3-fcb7-ab6b-fa63-19ec4973776d",
                "VlocityDataPackType": "VlocityMatchingKeyObject",
                "VlocityMatchingRecordSourceKey": "%vlocity_namespace%__ObjectLayout__c/d2bca9c3-fcb7-ab6b-fa63-19ec4973776d",
                "VlocityRecordSObjectType": "%vlocity_namespace%__ObjectLayout__c"
            },
            "%vlocity_namespace%__ObjectSection__c": [
                {
                    "%vlocity_namespace%__ColumnLayout__c": "",
                    "%vlocity_namespace%__EffectiveFromDate__c": "",
                    "%vlocity_namespace%__EffectiveUntilDate__c": "",
                    "%vlocity_namespace%__GlobalKey__c": "b07e58db-fe42-be2f-1598-c95c6050007a",
                    "%vlocity_namespace%__IsActive__c": true,
                    "%vlocity_namespace%__ObjectFacetId__c": {
                        "Name": "6db5c80f-7285-5bcd-4013-6d6a9aa9d64a",
                        "VlocityDataPackType": "VlocityMatchingKeyObject",
                        "VlocityMatchingRecordSourceKey": "%vlocity_namespace%__ObjectFacet__c/6db5c80f-7285-5bcd-4013-6d6a9aa9d64a",
                        "VlocityRecordSObjectType": "%vlocity_namespace%__ObjectFacet__c"
                    },
                    "%vlocity_namespace%__SectionId__c": {
                        "%vlocity_namespace%__GlobalKey__c": "f3ace7a9322ba258081738b2a79fb02a",
                        "VlocityDataPackType": "VlocityLookupMatchingKeyObject",
                        "VlocityLookupRecordSourceKey": "%vlocity_namespace%__UISection__c/f3ace7a9322ba258081738b2a79fb02a",
                        "VlocityRecordSObjectType": "%vlocity_namespace%__UISection__c"
                    },
                    "%vlocity_namespace%__Sequence__c": 1,
                    "%vlocity_namespace%__TabKeyOrder__c": "",
                    "%vlocity_namespace%__ViewType__c": "Custom View",
                    "%vlocity_namespace%__ViewUri__c": "ContextRules",
                    "Name": "b07e58db-fe42-be2f-1598-c95c6050007a",
                    "VlocityDataPackType": "SObject",
                    "VlocityRecordSObjectType": "%vlocity_namespace%__ObjectSection__c",
                    "VlocityRecordSourceKey": "%vlocity_namespace%__ObjectSection__c/b07e58db-fe42-be2f-1598-c95c6050007a"
                }
            ],
            "%vlocity_namespace%__Sequence__c": 6,
            "Name": "6db5c80f-7285-5bcd-4013-6d6a9aa9d64a",
            "VlocityDataPackType": "SObject",
            "VlocityRecordSObjectType": "%vlocity_namespace%__ObjectFacet__c",
            "VlocityRecordSourceKey": "%vlocity_namespace%__ObjectFacet__c/6db5c80f-7285-5bcd-4013-6d6a9aa9d64a"
        },
        {
            "%vlocity_namespace%__EffectiveFromDate__c": "",
            "%vlocity_namespace%__EffectiveUntilDate__c": "",
            "%vlocity_namespace%__FacetId__c": {
                "%vlocity_namespace%__GlobalKey__c": "dfe7bc9608d6f84ba04f9010be4bb8d1",
                "VlocityDataPackType": "VlocityLookupMatchingKeyObject",
                "VlocityLookupRecordSourceKey": "%vlocity_namespace%__UIFacet__c/dfe7bc9608d6f84ba04f9010be4bb8d1",
                "VlocityRecordSObjectType": "%vlocity_namespace%__UIFacet__c"
            },
            "%vlocity_namespace%__GlobalKey__c": "9f05b0bd-8fc4-3ede-dbd9-4570992e024e",
            "%vlocity_namespace%__IsActive__c": true,
            "%vlocity_namespace%__ObjectLayoutId__c": {
                "%vlocity_namespace%__GlobalKey__c": "d2bca9c3-fcb7-ab6b-fa63-19ec4973776d",
                "VlocityDataPackType": "VlocityMatchingKeyObject",
                "VlocityMatchingRecordSourceKey": "%vlocity_namespace%__ObjectLayout__c/d2bca9c3-fcb7-ab6b-fa63-19ec4973776d",
                "VlocityRecordSObjectType": "%vlocity_namespace%__ObjectLayout__c"
            },
            "%vlocity_namespace%__ObjectSection__c": [
                {
                    "%vlocity_namespace%__ColumnLayout__c": "",
                    "%vlocity_namespace%__EffectiveFromDate__c": "",
                    "%vlocity_namespace%__EffectiveUntilDate__c": "",
                    "%vlocity_namespace%__GlobalKey__c": "5f366a75-eca8-3397-c815-9dc23ace3fa0",
                    "%vlocity_namespace%__IsActive__c": true,
                    "%vlocity_namespace%__ObjectFacetId__c": {
                        "Name": "9f05b0bd-8fc4-3ede-dbd9-4570992e024e",
                        "VlocityDataPackType": "VlocityMatchingKeyObject",
                        "VlocityMatchingRecordSourceKey": "%vlocity_namespace%__ObjectFacet__c/9f05b0bd-8fc4-3ede-dbd9-4570992e024e",
                        "VlocityRecordSObjectType": "%vlocity_namespace%__ObjectFacet__c"
                    },
                    "%vlocity_namespace%__SectionId__c": {
                        "%vlocity_namespace%__GlobalKey__c": "dfe7bc9608d6f84ba04f9010be4bb8d1",
                        "VlocityDataPackType": "VlocityLookupMatchingKeyObject",
                        "VlocityLookupRecordSourceKey": "%vlocity_namespace%__UISection__c/dfe7bc9608d6f84ba04f9010be4bb8d1",
                        "VlocityRecordSObjectType": "%vlocity_namespace%__UISection__c"
                    },
                    "%vlocity_namespace%__Sequence__c": 1,
                    "%vlocity_namespace%__TabKeyOrder__c": "",
                    "%vlocity_namespace%__ViewType__c": "Custom View",
                    "%vlocity_namespace%__ViewUri__c": "LayoutManagement",
                    "Name": "5f366a75-eca8-3397-c815-9dc23ace3fa0",
                    "VlocityDataPackType": "SObject",
                    "VlocityRecordSObjectType": "%vlocity_namespace%__ObjectSection__c",
                    "VlocityRecordSourceKey": "%vlocity_namespace%__ObjectSection__c/5f366a75-eca8-3397-c815-9dc23ace3fa0"
                }
            ],
            "%vlocity_namespace%__Sequence__c": 7,
            "Name": "9f05b0bd-8fc4-3ede-dbd9-4570992e024e",
            "VlocityDataPackType": "SObject",
            "VlocityRecordSObjectType": "%vlocity_namespace%__ObjectFacet__c",
            "VlocityRecordSourceKey": "%vlocity_namespace%__ObjectFacet__c/9f05b0bd-8fc4-3ede-dbd9-4570992e024e"
        }
    ],
    "%vlocity_namespace%__SubclassId__c": {
        "%vlocity_namespace%__GlobalKey__c": "7b9b39-1a7326-6afb3e-e48ce0-fbaf3dddc",
        "VlocityDataPackType": "VlocityLookupMatchingKeyObject",
        "VlocityLookupRecordSourceKey": "%vlocity_namespace%__ObjectClass__c/7b9b39-1a7326-6afb3e-e48ce0-fbaf3dddc",
        "VlocityRecordSObjectType": "%vlocity_namespace%__ObjectClass__c"
    },
    "Name": "(Inherited)Layout-a2S5w000002d6FuEAI",
    "VlocityDataPackType": "SObject",
    "VlocityRecordSObjectType": "%vlocity_namespace%__ObjectLayout__c",
    "VlocityRecordSourceKey": "%vlocity_namespace%__ObjectLayout__c/d2bca9c3-fcb7-ab6b-fa63-19ec4973776d"
}